Workbook

Sheet Dashboard
A1: Partnership Pipeline — Dashboard
A2: Live summary across all three rings. Data pulls from Ring 1, Ring 2, and Ring 3 sheets.
A4: PIPELINE BY RING | B4: Partners | C4: High Priority | D4: Contacted+ | G4: RING 2 — BY COUNTRY | H4: Entities | I4: Status
A5: 🟢 Ring 1 — LU Institutions | B5: =COUNTA('Ring 1 — LU Institutions'!A2:A100) -> 27 | C5: =COUNTIF('Ring 1 — LU Institutions'!C2:C100,"High") -> 12 | D5: =COUNTIFS('Ring 1 — LU Institutions'!D2:D100,"<>Researching",'Ring 1 — LU Institutions'!D2:D100,"<>",'Ring 1 — LU Institutions'!D2:D100,"<>Not Started") -> 0 | G5: PT — Portugal | H5: =COUNTIF('Ring 2 — Communities'!B:B,"PT") -> 1 | I5: =IFERROR(INDEX('Ring 2 — Communities'!E:E,MATCH("PT",'Ring 2 — Communities'!B:B,0)),"-") -> Researching
A6: 🟣 Ring 2 — Country Communities | B6: =COUNTA('Ring 2 — Communities'!A2:A99) -> 12 | C6: =COUNTIF('Ring 2 — Communities'!D2:D99,"High") -> 8 | D6: =COUNTIFS('Ring 2 — Communities'!E2:E99,"<>Researching",'Ring 2 — Communities'!E2:E99,"<>",'Ring 2 — Communities'!E2:E99,"<>Not Started") -> 0 | G6: FR — France | H6: =COUNTIF('Ring 2 — Communities'!B:B,"FR") -> 1 | I6: =IFERROR(INDEX('Ring 2 — Communities'!E:E,MATCH("FR",'Ring 2 — Communities'!B:B,0)),"-") -> Researching
A7: 🔴 Ring 3 — Abroad (Stage 2) | B7: =COUNTA('Ring 3 — Abroad (Stage 2)'!A2:A100) -> 0 | C7: =COUNTIF('Ring 3 — Abroad (Stage 2)'!D2:D100,"High") -> 0 | D7: =COUNTIFS('Ring 3 — Abroad (Stage 2)'!E2:E100,"<>Researching",'Ring 3 — Abroad (Stage 2)'!E2:E100,"<>",'Ring 3 — Abroad (Stage 2)'!E2:E100,"<>Not Started") -> 0 | G7: IT — Italy | H7: =COUNTIF('Ring 2 — Communities'!B:B,"IT") -> 1 | I7: =IFERROR(INDEX('Ring 2 — Communities'!E:E,MATCH("IT",'Ring 2 — Communities'!B:B,0)),"-") -> Researching
A8: Total | B8: =SUM(B5:B7) -> 39 | C8: =SUM(C5:C7) -> 20 | D8: =SUM(D5:D7) -> 0 | G8: BE — Belgium | H8: =COUNTIF('Ring 2 — Communities'!B:B,"BE") -> 1 | I8: =IFERROR(INDEX('Ring 2 — Communities'!E:E,MATCH("BE",'Ring 2 — Communities'!B:B,0)),"-") -> Researching
G9: DE — Germany | H9: =COUNTIF('Ring 2 — Communities'!B:B,"DE") -> 1 | I9: =IFERROR(INDEX('Ring 2 — Communities'!E:E,MATCH("DE",'Ring 2 — Communities'!B:B,0)),"—") -> Researching
A10: STATUS TRACKER | B10: Ring 1 | C10: Ring 2 | D10: Ring 3 | E10: Total | G10: ES — Spain | H10: =COUNTIF('Ring 2 — Communities'!B:B,"ES") -> 1 | I10: =IFERROR(INDEX('Ring 2 — Communities'!E:E,MATCH("ES",'Ring 2 — Communities'!B:B,0)),"-") -> Researching
A11: Researching | B11: =COUNTIF('Ring 1 — LU Institutions'!D:D,"Researching") -> 27 | C11: =COUNTIF('Ring 2 — Communities'!E:E,"Researching") -> 12 | D11: =COUNTIF('Ring 3 — Abroad (Stage 2)'!E:E,"Researching") -> 0 | E11: =SUM(B11:D11) -> 39 | G11: CH — Switzerland | H11: =COUNTIF('Ring 2 — Communities'!B:B,"CH") -> 1 | I11: =IFERROR(INDEX('Ring 2 — Communities'!E:E,MATCH("CH",'Ring 2 — Communities'!B:B,0)),"-") -> Researching
A12: Contacted | B12: =COUNTIF('Ring 1 — LU Institutions'!D:D,"Contacted") -> 0 | C12: =COUNTIF('Ring 2 — Communities'!E:E,"Contacted") -> 0 | D12: =COUNTIF('Ring 3 — Abroad (Stage 2)'!E:E,"Contacted") -> 0 | E12: =SUM(B12:D12) -> 0 | G12: PL — Poland | H12: =COUNTIF('Ring 2 — Communities'!B:B,"PL") -> 1 | I12: =IFERROR(INDEX('Ring 2 — Communities'!E:E,MATCH("PL",'Ring 2 — Communities'!B:B,0)),"-") -> Researching
A13: In Discussion | B13: =COUNTIF('Ring 1 — LU Institutions'!D:D,"In Discussion") -> 0 | C13: =COUNTIF('Ring 2 — Communities'!E:E,"In Discussion") -> 0 | D13: =COUNTIF('Ring 3 — Abroad (Stage 2)'!E:E,"In Discussion") -> 0 | E13: =SUM(B13:D13) -> 0 | G13: UK / US — EN-speaking | H13: =COUNTIFS('Ring 2 — Communities'!B:B,"*EN-speaking*") -> 2 | I13: =IFERROR(INDEX('Ring 2 — Communities'!E:E,MATCH("US / EN-speaking",'Ring 2 — Communities'!B:B,0)),"—") -> Researching
A14: Active Partner | B14: =COUNTIF('Ring 1 — LU Institutions'!D:D,"Active Partner") -> 0 | C14: =COUNTIF('Ring 2 — Communities'!E:E,"Active Partner") -> 0 | D14: =COUNTIF('Ring 3 — Abroad (Stage 2)'!E:E,"Active Partner") -> 0 | E14: =SUM(B14:D14) -> 0 | G14: RO — Romania | H14: =COUNTIF('Ring 2 — Communities'!B:B,"RO") -> 1 | I14: =IFERROR(INDEX('Ring 2 — Communities'!E:E,MATCH("RO",'Ring 2 — Communities'!B:B,0)),"—") -> Researching
G15: IN — India | H15: =COUNTIF('Ring 2 — Communities'!B:B,"IN") -> 0 | I15: =IFERROR(INDEX('Ring 2 — Communities'!E:E,MATCH("IN",'Ring 2 — Communities'!B:B,0)),"—") -> —
G16: Nordic — DK/FI/IS/NO/SE | H16: =COUNTIF('Ring 2 — Communities'!B:B,"Nordic") -> 1 | I16: =IFERROR(INDEX('Ring 2 — Communities'!E:E,MATCH("Nordic",'Ring 2 — Communities'!B:B,0)),"—") -> Researching
A17: On Hold | B17: =COUNTIF('Ring 1 — LU Institutions'!D:D,"On Hold") -> 0 | C17: =COUNTIF('Ring 2 — Communities'!E:E,"On Hold") -> 0 | D17: =COUNTIF('Ring 3 — Abroad (Stage 2)'!E:E,"On Hold") -> 0 | E17: =SUM(B17:D17) -> 0 | G17: RING 1 — BY CATEGORY | H17: Count
A18: Not a Fit | B18: =COUNTIF('Ring 1 — LU Institutions'!D:D,"Not a Fit") -> 0 | C18: =COUNTIF('Ring 2 — Communities'!E:E,"Not a Fit") -> 0 | D18: =COUNTIF('Ring 3 — Abroad (Stage 2)'!E:E,"Not a Fit") -> 0 | E18: =SUM(B18:D18) -> 0 | G18: Hub / Public Body | H18: =COUNTIF('Ring 1 — LU Institutions'!B:B,"Hub / Public Body") -> 10
G19: Federation | H19: =COUNTIF('Ring 1 — LU Institutions'!B:B,"Federation") -> 14
G20: Chamber | H20: =COUNTIF('Ring 1 — LU Institutions'!B:B,"Chamber") -> 1
G21: Media | H21: =COUNTIF('Ring 1 — LU Institutions'!B:B,"Media") -> 1
G22: HR Network | H22: =COUNTIF('Ring 1 — LU Institutions'!B:B,"HR Network") -> 1

Sheet Draft
A1: Organization | B1: Why They Care | C1: Our Interest | D1: Main Message | E1: Partnership Type | F1: Access Conditions | G1: Support They Can Offer | H1: What We Offer | I1: Contact Person | J1: Need to Confirm | K1: Priority | L1: Status
A2: House of Entrepreneurship | B2: We offer useful value-add for people with international careers; fits their mission to inform, guide, and connect entrepreneurs | C2: Access to founders and internationally mobile entrepreneurs through workshops and advisor referrals; visibility in the entrepreneurship ecosystem; practical support and ecosystem introductions. | D2: We help employers and internationally mobile professionals with international careers understand and organize pension rights across countries | E2: Workshop / content / pilot / ecosystem intro | F2: Likely mission-based, free first contact; no public membership requirement found | G2: Advisor meeting, workshop opportunity, intros, feedback | H2: Workshop, guide, pilot session | I2: info@houseofentrepreneurship.lu | J2: Whether formal promotion or repeated collaboration needs separate arrangement | K2: High | L2: Researching
A3: Luxembourg Chamber of Commerce (cc.lu) | B3: Better support offer for member companies and internationally active businesses | C3: Reach employers, SMEs, and international business members via Chamber channels, events, and International Affairs | D3: We help employers and internationally mobile professionals with international careers understand and organize pension rights across countries | E3: Event / B2B intro / content / referral | F3: Core contact is open; deeper visibility may depend on Chamber process or membership context | G3: Intros, event route, international business access | H3: Employer-facing content, pilot, educational session | I3: Amrita Singh — Matchmaking Coordinator, International Affairs — amrita.singh@cc.lu | J3: Whether access to member-facing formats needs extra conditions | K3: High | L3: Researching
A4: House of Startups (HoST) | B4: We offer useful value-add for people with international careers; fits their mission to inform, guide, and connect entrepreneurs | C4: Access to startup founders and startup employees; visibility in the startup ecosystem; pilot-user access and community support. | D4: We help founders and startup talent with international careers get clarity on fragmented pension rights | E4: Workshop / content / pilot / ecosystem intro | F4: Likely open for first contact; deeper activation may depend on ecosystem fit or resident status | G4: Startup-community access, pilot audience, event/community route | H4: Workshop, guide, pilot session | I4: reception@host.lu | J4: Whether access to resident startups or event slots needs internal sponsor | K4: High | L4: Researching
A5: LHoFT | B5: Strong fintech / wealthtech / employee-financial-wellbeing angle; relevant to financial innovation and ecosystem collaboration | C5: Access to fintech, employers, and innovation partners; strong ecosystem visibility and credibility; support through introductions and pilot discussions. | D5: We are building a retirement-rights solution for internationally mobile professionals and employers | E5: Fintech partnership / pilot / ecosystem intro / employer-benefit discussion | F5: Likely selective and fit-driven | G5: Ecosystem credibility, intros, pilot conversations, event route | H5: Fintech use case, thought leadership, pilot, validation insights | J5: Whether membership/incubation is needed for deeper support | K5: High | L5: Researching
A6: Luxinnovation | B6: Relevant if they see us as an innovation/startup project with partner-finding and market-launch potential | C6: Reach startup ecosystem, innovation partners, and scaling-support structures through their startup and partner-finding support | D6: We are building a retirement-rights solution for internationally mobile professionals and employers | E6: Innovation support / partner finding / scaling support | F6: Mission-based support for innovation projects | G6: Partner finding, startup support, market-launch preparation, funding orientation | H6: Innovation case, ecosystem contribution, pilot | I6: Inna Perepelytsya — Senior Advisor — inna.perepelytsya@luxinnovation.lu Sven Baltes — Manager – Startup Relations — sven.baltes@luxinnovation.lu | J6: Whether they see the project as strong enough innovation fit | K6: Medium-High | L6: Researching
A7: AMCHAM Luxembourg | B7: We offer relevant member value for international companies and international employees; fits their information/problem-solving role | C7: Reach English-speaking employers, expat professionals, HR contacts, and member companies through events and committees | D7: We help international professionals and employers navigate fragmented pension rights built across Europe | E7: Event / employer pilot / content / committee discussion | F7: Likely member-driven; collaboration may depend on format or sponsorship | G7: Member events, employer visibility, committee access, newsletters | H7: Educational session, employer-benefit angle, guide, sharing news on changes in pension rights. | I7: Daniel McKenzie — Head of Communications, Events and Committee Structures — daniel@amcham.lu | J7: Whether speaking or content visibility needs membership or sponsor status or can start as external expert contribution | K7: High | L7: Researching
A8: British Chamber of Commerce | B8: We offer relevant member value for international companies and international employees; fits their event-based knowledge sharing | C8: Reach English-speaking employers, expat professionals, HR contacts, and member companies through events and committees | D8: We help international professionals and employers navigate fragmented pension rights built across Europe | E8: Event / content / community pilot / referrals | F8: Likely member-driven; collaboration may depend on format or sponsorship | G8: Community access,Events, business forums, member network | H8: Educational session, employer-benefit angle, guide, sharing news on changes in pension rights. | I8: Rebecca Kellagher — Manager — rebecca.kellagher@bcc.lu | J8: Whether speaking or content visibility needs membership or sponsor status or can start as external expert contribution | K8: High | L8: Researching
A9: CCIPL / Portugal–Luxembourg Chamber(ccill.lu) | B9: Highly relevant member/community topic for Portugal-linked entrepreneurs and professionals; fits their business support and matchmaking role | C9: Reach Portugal-linked founders, professionals, firms, and their event/newsletter audience | D9: We help Portugal–Luxembourg professionals understand and organize pension rights across countries | E9: Event / content / community pilot / referrals | F9: Likely member-driven; collaboration may depend on format or sponsorship | G9: Community access, events, business introductions, newsletter potential, visibility | H9: Portugal–Luxembourg pension session, guide, pilot | I9: info@ccill.lu | J9: Whether speaking or content visibility needs membership or sponsor status or can start as external expert contribution | K9: High | L9: Researching
A10: Luxembourg-Poland Chamber of Commerce (LPCC) (lpcc.lu) | B10: Relevant member/community topic for Poland-linked entrepreneurs and professionals; fits their business support and matchmaking role | C10: Reach Poland-linked founders, professionals, firms, and their event/newsletter audience | D10: We help internationally mobile professionals with Poland-linked careers organize pension rights across countries | E10: Event / content / community pilot / referrals | F10: Likely member-driven; collaboration may depend on format or sponsorship | G10: Community access, events, business introductions, newsletter potential, visibility | H10: Poland–Lux session, guide, pilot group | I10: Oliwia Gertych — Digital Marketer & Project Manager — oliwia.gertych@lpcc.lu | J10: Whether speaking or content visibility needs membership or sponsor status or can start as external expert contribution | K10: Medium-High | L10: Researching
A11: Official Spanish Chamber of Commerce in Belgium and Luxembourg (e-camara.com) | B11: Relevant member/community topic for Spain-linked entrepreneurs and professionals; fits their business support and matchmaking role | C11: Reach Spain-linked founders, professionals, firms, and their event/newsletter audience | D11: We help internationally mobile professionals with Spain-linked careers organize pension rights across countries | E11: Event / content / community pilot / referrals | F11: Likely member-driven; collaboration may depend on format or sponsorship (direct contact? ) | G11: Community access, events, business introductions, newsletter potential, visibility | H11: Spain–Lux session, guide, pilot group | I11: luxemburgo@e-camara.com | J11: Whether speaking or content visibility needs membership or sponsor status or can start as external expert contribution | K11: Medium-High | L11: Researching
A12: Luxembourg-Italian Chamber of Commerce | B12: Relevant topic for Italy-linked companies and professionals in Luxembourg, especially since Italy is one of our product expansion markets | C12: Reach Italy-linked founders, professionals, firms, and their event/newsletter audience | D12: We help Italy–Luxembourg professionals understand and organize pension rights across countries | E12: Event / content / community pilot / referrals | F12: Likely chamber-based; direct outreach possible | G12: Bilateral network, events, visibility, member access | H12: Italy–Lux pension education session, practical guide, pilot audience | I12: Luisa Castelli Secrétaire général / Directeur — l.castelli@ccil.lu | J12: Whether speaking or content visibility needs membership or sponsor status or can start as external expert contribution | K12: High | L12: Researching
A13: CCI France Luxembourg | B13: Highly relevant member/community topic for France-linked entrepreneurs and professionals; fits their business support and matchmaking role | C13: Reach France-linked founders, professionals, firms, and their event/newsletter audience; strong credibility in the France–Lux corridor | D13: We help internationally mobile professionals with France-linked careers organize pension rights across countries | E13: Event / content / community pilot / referrals | F13: Clear membership model and business club logic; first contact open, deeper visibility likely easier through partnership or member-style collaboration | G13: Community access, events, business introductions, newsletter potential, visibility | H13: France–Lux pension session, practical guide, employer-facing content, pilot | I13: Alexandra Benel, Director — alexandra.benel@cfci.lu; general cfci@cfci.lu | J13: Whether speaking or content visibility needs membership or sponsor status or can start as external expert contribution | K13: High | L13: Researching
A14: Business Club Luxemburg-Schweiz | B14: Highly relevant member/community topic for Switzerland-linked entrepreneurs and professionals; fits their business support and matchmaking role | C14: Reach Switzerland-linked founders, professionals, firms, and their event/newsletter audience | D14: We help Switzerland–Luxembourg professionals bring clarity to fragmented pension rights and occupational/private retirement assets across countries | E14: Event / content / community pilot / referrals | F14: Accredited bilateral business club, but detailed public access conditions need confirmation through direct contact via Chamber bilateral route | G14: Community access, events, business introductions, newsletter potential, visibility | H14: Swiss–Lux pension education session, practical cross-border guide, pilot audience | J14: Whether speaking or content visibility needs membership or sponsor status or can start as external expert contribution | K14: Low (they don’t have a big network) | L14: Researching
A15: Business Club Belgium-Luxembourg (BCBL) | B15: Highly relevant member/community topic for France-linked entrepreneurs and professionals; fits their business support and matchmaking role | C15: Reach Belgian-linked companies, professionals, firms, and their event/newsletter audience | D15: We help internationally mobile professionals with Belgium-linked careers organize pension rights across countries | E15: Event / content / community pilot / referrals | F15: Appears to be member-based business club; first contact open; deeper collaboration likely depends on club format or membership/sponsorship | G15: Community access, events, business introductions, newsletter potential, visibility | H15: Belgium–Lux pension session, practical guide, pilot group, employer-facing content | I15: contact@bcbl.be | J15: Whether speaking or content visibility needs membership or sponsor status or can start as external expert contribution | K15: High | L15: Researching
A16: Social Business Incubator (SBI) | B16: If positioned as financial inclusion / long-term resilience for internationally mobile people, it fits their social-impact support logic | C16: Reach social entrepreneurs, impact projects, and communities where financial clarity is part of social inclusion | D16: We want to improve long-term financial clarity and pension access for internationally mobile people | E16: Impact partnership / workshop / ecosystem intro | F16: Likely mission-based support | G16: Advice, training, impact-network intros, social positioning | H16: Financial wellbeing / inclusion workshop, impact framing | I16: contact@sbi.lu | J16: Whether our project is impact-oriented enough for active support | K16: Medium | L16: Researching
A17: Luxembourg Employers’ Association (UEL) | B17: Our solution can support employers dealing with internationally mobile employees and long-term employee wellbeing topics | C17: Reach employers, business leaders, and employer associations; strong B2B credibility and policy-level visibility | D17: We help employers support internationally mobile employees facing fragmented pension rights across countries | E17: Employer pilot / policy discussion / event / content | F17: Likely institutional and selective; contact possible through public route | G17: Employer credibility, possible introductions, policy/business visibility | H17: Employer-benefit angle, educational content, pilot idea | I17: Jean-Paul Olinger / public route press@uel.lu | J17: Best operational contact and whether topic fits their agenda | K17: High | L17: Researching
A18: ALFI – Association of the Luxembourg Fund Industry | B18: Relevant if positioned around international finance professionals, mobility, and long-term retirement/wealth-planning literacy | C18: Reach international finance professionals, member firms, and industry visibility in Luxembourg finance ecosystem | D18: We help employers support internationally mobile employees facing fragmented pension rights across countries | E18: Thought leadership / event / finance-community content | F18: Likely member-driven and industry-focused | G18: Events, premium visibility, finance-network access | H18: Educational session, finance-focused guide, premium pilot audience | J18: Whether they would see this as relevant beyond investment/fund topics | K18: Medium-High | L18: Researching
A19: Luxembourg for Finance (LFF) | B19: Strong fit for the international-finance and international-talent angle; your topic is relevant for globally mobile finance professionals | C19: Reach international finance audience, institutions, and financial-ecosystem visibility | D19: We help employers support internationally mobile employees facing fragmented pension rights across countries | E19: Event / ecosystem intro / thought leadership / visibility | F19: Likely institutional and fit-driven | G19: Visibility, finance-community access, ecosystem introductions | H19: Finance-professional guide, panel topic, educational session | I19: Jonathan WESTHEAD — Head of Communications — jonathan.westhead@lff.lu | J19: Whether they would host or circulate a topic like this | K19: Medium-High | L19: Researching
A20: FEDIL – The Voice of Luxembourg’s Industry | B20: Relevant for employers with international talent and cross-border workforce management needs | C20: Reach industrial employers, HR/business leaders, and employer network visibility | D20: We help employers support internationally mobile employees facing fragmented pension rights across countries | E20: Employer pilot / event / content / referrals | F20: Likely association-based and agenda-driven | G20: Employer network, business visibility, sector reach | H20: Employer-facing workshop, international-workforce support angle | J20: Best contact person and whether topic fits employer agenda | K20: Medium-High | L20: Researching
A21: APSI Luxembourg | B21: Relevant if positioned as digital infrastructure / fintech / regtech / employee-digital-services topic | C21: Reach Luxembourg tech community, digital leaders, and ecosystem visibility | D21: We help employers support internationally mobile employees facing fragmented pension rights across countries | E21: Ecosystem intro / event / visibility / tech-community content | F21: Likely association/community-based | G21: Tech visibility, digital ecosystem access, possible event channel | H21: Digital-use-case angle, startup/fintech story, product demo | J21: Whether they are a strong enough GTM route versus only visibility | K21: Medium | L21: Researching
A22: LPEA – Luxembourg Private Equity & Venture Capital Association | B22: Our solution is relevant to an international finance audience with highly mobile careers; LPEA’s mission is to connect, inform, and represent the PE/VC ecosystem. | C22: Reach PE/VC firms, private banks, family offices, advisors, and highly international professionals; gain premium finance visibility and potential employer-level access. | D22: We help internationally mobile professionals and employers in finance understand and organize fragmented pension rights across countries. | E22: Event / thought leadership / employer pilot / finance-community content | F22: Clear membership-based association, but direct contact is open. | G22: Events, network access, industry visibility, premium-segment credibility, knowledge-sharing platform. | H22: Finance-focused educational session, premium professional guide, pilot group, thought leadership content. | I22: Claus Mansfeldt — President— claus.mansfeldt@lpea.lu Stephane Pesch — CEO — stephane.pesch@lpea.lu Johann Herz — Head of Events & Communication — johann.herz@lpea.lu | J22: Whether non-members can speak, publish, or co-host; best operational contact beyond general office. | K22: Medium-High | L22: Researching
A23: LBAN – Luxembourg Business Angel Network | B23: Relevant if we position the solution for founders, investors, and internationally mobile startup operators; LBAN’s mission is to connect business angels with the entrepreneurial ecosystem and support startup growth. | C23: Reach angel investors, founders, startup teams, and ecosystem actors; gain startup/investor visibility and possible intros to founder communities and early adopters. | D23: We help internationally mobile professionals and employers in finance understand and organize fragmented pension rights across countries. | E23: Event / startup-investor content / ecosystem intro / pilot | F23: Membership/network-based, but general contact is open. | G23: Investor/startup ecosystem visibility, founder access, event/network route, community credibility. | H23: Founder/investor education session, startup-team guide, pilot-user angle, ecosystem content. | I23: info@lban.lu; public contacts include Michel Rzonzef (President)and Teona Khubutia (Manager). | J23: Whether they see the topic as relevant enough for members; whether event/content collaboration requires membership or sponsor route. | K23: Medium | L23: Researching
A24: ABBL?
A25: Maison Moderne / Paperjam / Delano | B25: Strong editorial relevance if framed as international talent, retirement fragmentation, and employer/expat financial clarity in Luxembourg | C25: Reach business audience, employers, decision-makers, and broad Luxembourg visibility through media exposure | D25: We are building a retirement-rights solution for internationally mobile professionals and employers | E25: Media / thought leadership / interview / article | F25: Editorial fit required; not a classic partnership | G25: Visibility, credibility, audience reach, story amplification | H25: Article angle, expert commentary, ecosystem story | I25: Aaron Grunwald — Editor-in-chief at Delano — aaron.grunwald@maisonmoderne.com Thierry Labro — Editor-in-chief at Delano — thierry.labro@maisonmoderne.com | J25: Best story angle: expat, talent, pensions, founder journey, or fintech | K25: High | L25: Researching

Sheet Ring 1 — LU Institutions
A1: Organization | B1: Category | C1: Priority | D1: Status | E1: Next Action | F1: GTM Role | G1: Why They Care | H1: Our Interest | I1: Main Message | J1: Partnership Type | K1: Access Conditions | L1: Support They Can Offer | M1: What We Offer | N1: Contact Person | O1: Need to Confirm
A2: House of Entrepreneurship | B2: Hub / Public Body | C2: High | D2: Researching | E2: Identify contact at House of Entrepreneurship; check upcoming startup events to attend | F2: Ecosystem intro, workshops, pilot users | G2: We offer useful value-add for people with international careers; fits their mission to inform, guide, and connect entrepreneurs | H2: Access to founders and internationally mobile entrepreneurs through workshops and advisor referrals; visibility in the entrepreneurship ecosystem; practical support and ecosystem introductions. | I2: We help employers and internationally mobile professionals with international careers understand and organize pension rights across countries | J2: Workshop / content / pilot / ecosystem intro | K2: Likely mission-based, free first contact; no public membership requirement found | L2: Advisor meeting, workshop opportunity, intros, feedback | M2: Workshop, guide, pilot session | N2: info@houseofentrepreneurship.lu | O2: Whether formal promotion or repeated collaboration needs separate arrangement
A3: Luxembourg Chamber of Commerce (cc.lu) | B3: Chamber | C3: High | D3: Researching | E3: Check CC events calendar; explore membership or partnership application route | F3: B2B intros, employer reach, events | G3: Better support offer for member companies and internationally active businesses | H3: Reach employers, SMEs, and international business members via Chamber channels, events, and International Affairs | I3: We help employers and internationally mobile professionals with international careers understand and organize pension rights across countries | J3: Event / B2B intro / content / referral | K3: Core contact is open; deeper visibility may depend on Chamber process or membership context | L3: Intros, event route, international business access | M3: Employer-facing content, pilot, educational session | N3: Amrita Singh — Matchmaking Coordinator, International Affairs — amrita.singh@cc.lu | O3: Whether access to member-facing formats needs extra conditions
A4: House of Startups (HoST) | B4: Hub / Public Body | C4: High | D4: Researching | E4: Contact HoST reception; ask about hosting a pension-rights workshop for startups | F4: Startup community, pilot users, events | G4: We offer useful value-add for people with international careers; fits their mission to inform, guide, and connect entrepreneurs | H4: Access to startup founders and startup employees; visibility in the startup ecosystem; pilot-user access and community support. | I4: We help founders and startup talent with international careers get clarity on fragmented pension rights | J4: Workshop / content / pilot / ecosystem intro | K4: Likely open for first contact; deeper activation may depend on ecosystem fit or resident status | L4: Startup-community access, pilot audience, event/community route | M4: Workshop, guide, pilot session | N4: reception@host.lu | O4: Whether access to resident startups or event slots needs internal sponsor
A5: LHoFT | B5: Hub / Public Body | C5: High | D5: Researching | E5: Contact LHoFT team; propose fintech-meets-pension session for resident startups | F5: Fintech credibility, pilot, ecosystem intros | G5: Strong fintech / wealthtech / employee-financial-wellbeing angle; relevant to financial innovation and ecosystem collaboration | H5: Access to fintech, employers, and innovation partners; strong ecosystem visibility and credibility; support through introductions and pilot discussions. | I5: We are building a retirement-rights solution for internationally mobile professionals and employers | J5: Fintech partnership / pilot / ecosystem intro / employer-benefit discussion | K5: Likely selective and fit-driven | L5: Ecosystem credibility, intros, pilot conversations, event route | M5: Fintech use case, thought leadership, pilot, validation insights | O5: Whether membership/incubation is needed for deeper support
A6: Luxinnovation | B6: Hub / Public Body | C6: Medium-High | D6: Researching | E6: Explore Fit 4 Start or partner program; check if pension topic fits their innovation support | F6: Innovation support, partner finding, scaling | G6: Relevant if they see us as an innovation/startup project with partner-finding and market-launch potential | H6: Reach startup ecosystem, innovation partners, and scaling-support structures through their startup and partner-finding support | I6: We are building a retirement-rights solution for internationally mobile professionals and employers | J6: Innovation support / partner finding / scaling support | K6: Mission-based support for innovation projects | L6: Partner finding, startup support, market-launch preparation, funding orientation | M6: Innovation case, ecosystem contribution, pilot | N6: Inna Perepelytsya — Senior Advisor — inna.perepelytsya@luxinnovation.lu Sven Baltes — Manager – Startup Relations — sven.baltes@luxinnovation.lu | O6: Whether they see the project as strong enough innovation fit
A7: Social Business Incubator (SBI) | B7: Hub / Public Body | C7: Medium | D7: Researching | E7: Contact SBI; propose social-impact angle on financial inclusion for mobile workers | F7: Social impact channel, inclusion angle | G7: If positioned as financial inclusion / long-term resilience for internationally mobile people, it fits their social-impact support logic | H7: Reach social entrepreneurs, impact projects, and communities where financial clarity is part of social inclusion | I7: We want to improve long-term financial clarity and pension access for internationally mobile people | J7: Impact partnership / workshop / ecosystem intro | K7: Likely mission-based support | L7: Advice, training, impact-network intros, social positioning | M7: Financial wellbeing / inclusion workshop, impact framing | N7: contact@sbi.lu | O7: Whether our project is impact-oriented enough for active support
A8: Luxembourg Employers' Association (UEL) | B8: Federation | C8: High | D8: Researching | E8: Research UEL employer events; identify contact for employer-facing pension content | F8: Employer credibility, policy visibility | G8: Our solution can support employers dealing with internationally mobile employees and long-term employee wellbeing topics | H8: Reach employers, business leaders, and employer associations; strong B2B credibility and policy-level visibility | I8: We help employers support internationally mobile employees facing fragmented pension rights across countries | J8: Employer pilot / policy discussion / event / content | K8: Likely institutional and selective; contact possible through public route | L8: Employer credibility, possible introductions, policy/business visibility | M8: Employer-benefit angle, educational content, pilot idea | N8: Jean-Paul Olinger / public route press@uel.lu | O8: Best operational contact and whether topic fits their agenda
A9: ALFI – Association of the Luxembourg Fund Industry | B9: Federation | C9: Medium-High | D9: Researching | E9: Check ALFI event calendar; propose educational session on pension rights for fund professionals | F9: Finance network, premium visibility | G9: Relevant if positioned around international finance professionals, mobility, and long-term retirement/wealth-planning literacy | H9: Reach international finance professionals, member firms, and industry visibility in Luxembourg finance ecosystem | I9: We help employers support internationally mobile employees facing fragmented pension rights across countries | J9: Thought leadership / event / finance-community content | K9: Likely member-driven and industry-focused | L9: Events, premium visibility, finance-network access | M9: Educational session, finance-focused guide, premium pilot audience | O9: Whether they would see this as relevant beyond investment/fund topics
A10: Luxembourg for Finance (LFF) | B10: Hub / Public Body | C10: Medium-High | D10: Researching | E10: Contact LFF team; explore thought-leadership content on pension portability for finance sector | F10: Finance ecosystem visibility, intros | G10: Strong fit for the international-finance and international-talent angle; your topic is relevant for globally mobile finance professionals | H10: Reach international finance audience, institutions, and financial-ecosystem visibility | I10: We help employers support internationally mobile employees facing fragmented pension rights across countries | J10: Event / ecosystem intro / thought leadership / visibility | K10: Likely institutional and fit-driven | L10: Visibility, finance-community access, ecosystem introductions | M10: Finance-professional guide, panel topic, educational session | N10: Jonathan Westhead — Head of Communications — jonathan.westhead@lff.lu | O10: Whether they would host or circulate a topic like this
A11: FEDIL – The Voice of Luxembourg’s Industry | B11: Federation | C11: Medium-High | D11: Researching | E11: Research FEDIL member events; identify HR/employer-services contact | F11: Industrial employer reach, B2B channel | G11: Relevant for employers with international talent and cross-border workforce management needs | H11: Reach industrial employers, HR/business leaders, and employer network visibility | I11: We help employers support internationally mobile employees facing fragmented pension rights across countries | J11: Employer pilot / event / content / referrals | K11: Likely association-based and agenda-driven | L11: Employer network, business visibility, sector reach | M11: Employer-facing workshop, international-workforce support angle | O11: Best contact person and whether topic fits employer agenda
A12: APSI Luxembourg | B12: Federation | C12: Medium | D12: Researching | E12: Check APSI events; explore digital-pension-tools angle for tech community | F12: Tech community, digital ecosystem | G12: Relevant if positioned as digital infrastructure / fintech / regtech / employee-digital-services topic | H12: Reach Luxembourg tech community, digital leaders, and ecosystem visibility | I12: We help employers support internationally mobile employees facing fragmented pension rights across countries | J12: Ecosystem intro / event / visibility / tech-community content | K12: Likely association/community-based | L12: Tech visibility, digital ecosystem access, possible event channel | M12: Digital-use-case angle, startup/fintech story, product demo | O12: Whether they are a strong enough GTM route versus only visibility
A13: LPEA – Luxembourg Private Equity & Venture Capital Association | B13: Federation | C13: Medium-High | D13: Researching | E13: Research LPEA events calendar; propose PE/VC-angle session on founder pension complexity | F13: PE/VC network, premium finance access | G13: Our solution is relevant to an international finance audience with highly mobile careers; LPEA's mission is to connect, inform, and represent the PE/VC ecosystem. | H13: Reach PE/VC firms, private banks, family offices, advisors, and highly international professionals; gain premium finance visibility and potential employer-level access. | I13: We help internationally mobile professionals and employers in finance understand and organize fragmented pension rights across countries. | J13: Event / thought leadership / employer pilot / finance-community content | K13: Clear membership-based association, but direct contact is open. | L13: Events, network access, industry visibility, premium-segment credibility, knowledge-sharing platform. | M13: Finance-focused educational session, premium professional guide, pilot group, thought leadership content. | N13: Claus Mansfeldt — President — claus.mansfeldt@lpea.lu Stephane Pesch — CEO — stephane.pesch@lpea.lu Johann Herz — Head of Events & Communication — johann.herz@lpea.lu | O13: Whether non-members can speak, publish, or co-host; best operational contact beyond general office.
A14: LBAN – Luxembourg Business Angel Network | B14: Hub / Public Body | C14: Medium | D14: Researching | E14: Contact LBAN network manager; explore startup-founder pension workshop | F14: Angel/founder network, startup intros | G14: Relevant if we position the solution for founders, investors, and internationally mobile startup operators; LBAN's mission is to connect business angels with the entrepreneurial ecosystem and support startup growth. | H14: Reach angel investors, founders, startup teams, and ecosystem actors; gain startup/investor visibility and possible intros to founder communities and early adopters. | I14: We help internationally mobile professionals and employers in finance understand and organize fragmented pension rights across countries. | J14: Event / startup-investor content / ecosystem intro / pilot | K14: Membership/network-based, but general contact is open. | L14: Investor/startup ecosystem visibility, founder access, event/network route, community credibility. | M14: Founder/investor education session, startup-team guide, pilot-user angle, ecosystem content. | N14: info@lban.lu; public contacts include Michel Rzonzef (President) and Teona Khubutia (Manager). | O14: Whether they see the topic as relevant enough for members; whether event/content collaboration requires membership or sponsor route.
A15: Maison Moderne / Paperjam / Delano | B15: Media | C15: High | D15: Researching | E15: Research Paperjam/Delano editorial calendar; propose thought-leadership article or interview | F15: Visibility, thought leadership, audience | G15: Strong editorial relevance if framed as international talent, retirement fragmentation, and employer/expat financial clarity in Luxembourg | H15: Reach business audience, employers, decision-makers, and broad Luxembourg visibility through media exposure | I15: We are building a retirement-rights solution for internationally mobile professionals and employers | J15: Media / thought leadership / interview / article | K15: Editorial fit required; not a classic partnership | L15: Visibility, credibility, audience reach, story amplification | M15: Article angle, expert commentary, ecosystem story | N15: Aaron Grunwald — Editor-in-chief at Delano — aaron.grunwald@maisonmoderne.com Thierry Labro — Editor-in-chief at Delano — thierry.labro@maisonmoderne.com | O15: Best story angle: expat, talent, pensions, founder journey, or fintech
A16: ABBL – Luxembourg Bankers' Association | B16: Federation | C16: High | D16: Researching | E16: Research contact route; check if ABBL has HR / mobility working group | F16: Banking employer reach, finance-professional access, premium visibility | G16: Largest financial-sector association; many member banks employ highly mobile international professionals whose pension rights fragment across countries | H16: Reach banks, financial intermediaries, and their internationally mobile employees; gain premium financial-sector credibility and employer-level access | I16: We help employers and internationally mobile professionals in finance understand and organize fragmented pension rights across countries | J16: Employer pilot / event / thought leadership / finance-community content | K16: Member-driven association; first contact open via public route | L16: Events, employer network, finance-sector visibility, working-group access, premium credibility | M16: Finance-professional pension guide, employer-facing educational session, pilot audience, thought leadership content | O16: Best operational contact; whether topic fits their employer/HR agenda or innovation working group
A17: HRCommunity.lu | B17: HR Network | C17: High | D17: Researching | E17: Contact via website; propose educational session on cross-border pension rights for HR professionals | F17: Direct HR decision-maker access, employer-benefit channel, event route | G17: Reference HR community in Luxembourg since 1992; their member companies manage internationally mobile employees whose pension rights are a real HR pain point | H17: Direct access to HR directors and people managers across all sectors; visibility as an expert solution for cross-border employee benefits | I17: We help HR professionals support internationally mobile employees facing fragmented pension rights across countries | J17: Event / workshop / content / employer pilot | K17: Membership-based community of HR professionals; contact open through website | L17: HR-community events, employer network, sector-wide HR visibility, knowledge-sharing platform | M17: Cross-border pension workshop for HR teams, practical employer guide, pilot group, thought leadership | O17: Whether they host external expert sessions; best contact for partnership discussions
A18: ADEM – Agence pour le Développement de l'Emploi | B18: Hub / Public Body | C18: High | D18: Researching | E18: Research public contact route; explore if they have expat integration or employer-services team | F18: Expat integration channel, employer services, public-sector credibility | G18: Luxembourg's public employment agency; directly assists cross-border workers and expats with professional integration — pension and social security clarity is a natural extension | H18: Reach internationally mobile jobseekers and employers through ADEM's integration services; public-sector credibility and visibility | I18: We help internationally mobile professionals and employers understand and organize fragmented pension rights across countries | J18: Information partnership / content / referral / workshop | K18: Public institution; contact open through official channels | L18: Expat integration reach, employer services access, public-sector referral channel, credibility | M18: Pension-rights information resource for expats, employer guide, educational content for integration services | O18: Whether they have an employer-services or expat-integration team; best contact route for partnerships
A19: Luxembourg-City Incubator (LCI) | B19: Hub / Public Body | C19: Medium-High | D19: Researching | E19: Contact via HoST or directly; check if incubated startups fit as pilot audience | F19: International founder access, startup pilot users, ecosystem intro | G19: City-backed incubator for early-stage companies; many incubated founders are internationally mobile and face cross-border pension complexity | H19: Access to international startup founders as pilot users; visibility in the incubator ecosystem; complementary channel to HoST | I19: We help founders and startup talent with international careers get clarity on fragmented pension rights | J19: Workshop / pilot / ecosystem intro | K19: Backed by City of Luxembourg and Chamber of Commerce; likely mission-based, open to collaboration | L19: Startup-founder access, event channel, incubator community, pilot audience | M19: Founder pension workshop, practical guide, pilot session for incubated startups | O19: Whether collaboration needs to go through HoST or can be direct; best contact for event/workshop proposals
A20: Technoport | B20: Hub / Public Body | C20: Medium-High | D20: Researching | E20: Contact via website; check if they run community events for resident startups | F20: International startup access, tech-founder community, ecosystem intro | G20: National technology incubator; often the first local hub for international startups arriving in Luxembourg — these founders face immediate cross-border pension fragmentation | H20: Reach international tech founders at the moment they relocate to Luxembourg; pilot-user access and ecosystem credibility | I20: We help founders and startup talent with international careers get clarity on fragmented pension rights | J20: Workshop / pilot / ecosystem intro / content | K20: Public incubator; likely mission-based and open to collaboration | L20: International-founder community, event channel, ecosystem credibility, early-stage access | M20: Founder pension workshop, relocation guide for international startups, pilot session | O20: Whether they run community programming; best contact for workshop/content proposals
A21: CFA Society Luxembourg | B21: Federation | C21: High | D21: Researching | E21: Check CFA Society events calendar; propose educational session on pension portability for CFA members | F21: Finance-professional network, premium credibility, educational events | G21: Professional society for CFA charterholders and candidates since 2003; members are highly international finance professionals — exactly the profile with fragmented pension rights across multiple countries | H21: Direct access to internationally mobile investment professionals; high pension-relevance; monthly educational conferences and networking events with 20-200 attendees | I21: We help internationally mobile finance professionals understand and organize pension rights scattered across the countries where they've built their careers | J21: Event / educational session / thought leadership / professional development content | K21: Membership open to CFA Institute members and candidates; events generally open to members; speaker proposals likely welcome | L21: Monthly conferences, networking events, newsletter, premium finance-professional audience, educational platform | M21: Pension-portability educational session for CFA members, practical guide for internationally mobile finance professionals, thought leadership content | O21: Whether they host external speaker sessions; best contact for educational content proposals
A22: ACA – Association des Compagnies d'Assurances | B22: Federation | C22: High | D22: Researching | E22: Contact ACA; explore pension/insurance pillar 2-3 content collaboration | F22: Insurance industry access, pension-pillar expertise, policy credibility | G22: Professional association of 146 Luxembourg insurers and reinsurers; directly involved in government consultations on Luxembourg's public pension system and second/third pillar reform | H22: Access to the insurance industry that designs and distributes pension products; partnership credibility on pension topics; visibility in policy discussions | I22: We complement pillar 2-3 pension products by helping internationally mobile workers understand their fragmented pillar 1 rights across countries | J22: Content partnership / thought leadership / event / policy input | K22: Member-driven industry association; contact via ACA management | L22: Insurance industry network, pension policy access, events, working groups, House of Finance co-location with ABBL/ALFI/LFF | M22: Cross-border pension insight for insurance members, educational content for employers using pillar 2-3 products, thought leadership | O22: Whether pension/employee-benefits working group exists; best contact for content partnership
A23: ILA – Institut Luxembourgeois des Administrateurs | B23: Federation | C23: High | D23: Researching | E23: Check ILA events calendar; propose governance-angle session on pension portability for board directors | F23: Senior executive access, governance community, board-level credibility | G23: Luxembourg's leading institute for corporate directors and governance professionals since 2005; 3,500+ members including board directors of international companies with careers spanning multiple countries | H23: Access to 3,500+ senior governance professionals — exactly the profile with fragmented pension rights from multi-country board careers; training/certification events | I23: Board directors with international careers have pension rights scattered across multiple countries. We help them track and organize those rights. | J23: Training session / governance event / thought leadership / member benefit | K23: Membership-based; offers training, certification, and networking; open to speaker proposals | L23: 3,500+ member network, training events, governance certifications, newsletter, ecoDa European network | M23: Pension-portability session for board directors, practical guide for governance professionals, thought leadership | O23: Whether they host external expert sessions in their training program; best contact for partnership
A24: ILAC – Institut Luxembourgeois des Actuaires | B24: Federation | C24: Medium-High | D24: Researching | E24: Contact ILAC bureau; propose actuarial-angle session on cross-border pension portability | F24: Pension-specialist community, technical credibility, insurance-sector access | G24: Institute of ~300 actuaries active in Luxembourg since 1992; actuaries are pension specialists by profession — they design and value the pension products that internationally mobile workers accumulate across countries | H24: Access to 300 pension/insurance specialists; natural amplifiers who understand the technical complexity; conferences attract 150+ professionals | I24: Actuaries understand cross-border pension complexity better than anyone. We give their clients the tools to navigate it. | J24: Conference session / technical partnership / CPD content | K24: Professional institute; regular open conferences; CPD program for members | L24: Actuarial conferences, CPD program, technical community, Actuview platform partnership | M24: Cross-border pension data/insight session for actuaries, CPD-eligible content, technical partnership | O24: Whether CPD session proposals are open; best contact at ILAC bureau
A25: AMMD – Association des Médecins et Médecins-Dentistes | B25: Federation | C25: Medium | D25: Researching | E25: Contact AMMD secretariat; explore whether pension/financial-planning content fits their member services | F25: Medical professional access, healthcare-sector credibility, CNS/social security link | G25: Luxembourg's most representative medical association since 1904; key liaison between the medical profession, the Ministry of Health, and the CNS (national health fund). Doctors in LU are highly international — many trained abroad with pension rights in other countries. | H25: Access to ~800-900 doctors and dentists, many of whom trained and worked abroad before settling in LU; direct link to CNS and social security system | I25: Doctors who trained and worked in other countries before practicing in Luxembourg have pension rights scattered across multiple systems. We help them track and organize those rights. | J25: Member information service / event / content partnership | K25: Membership requires practicing authorization in LU; union-like structure; contact via secretariat | L25: Medical professional network, member communications, Scientific Council, link to CNS/Ministry of Health | M25: Pension-rights information resource for international doctors, practical guide for medical professionals relocating to/from LU | O25: Whether they provide member services beyond union representation; best contact for information partnership
A26: INGSCI – Ingénieurs et Scientifiques du Luxembourg | B26: Federation | C26: Medium | D26: Researching | E26: Contact INGSCI via secretariat; explore whether pension topic fits their Journée de l'Ingénieur or conference program | F26: Engineering professional access, cross-border network (Saar-Lor-Lux), industry events | G26: Luxembourg's voluntary association for engineers, architects, scientists and industrials; hosts the annual Journée de l'Ingénieur, conferences, and cross-border Saar-Lor-Lux events with engineering associations in Germany and France. Many members trained abroad. | H26: Access to internationally trained engineers with careers spanning multiple countries; cross-border cooperation with DE/FR engineering associations directly touches pension fragmentation zone | I26: Engineers who trained and worked in multiple countries before settling in Luxembourg have pension rights scattered across those systems. We help them organize and understand those rights. | J26: Conference session / Journée de l'Ingénieur / cross-border event / content | K26: Voluntary membership; hosts events at Forum da Vinci; open to speaker proposals | L26: Annual Journée de l'Ingénieur, conferences, cross-border Saar-Lor-Lux network, Forum da Vinci venue, publications | M26: Cross-border pension workshop for engineers, practical guide for mobile professionals, Saar-Lor-Lux themed session | O26: Whether Journée de l'Ingénieur accepts external speakers; best contact at secretariat
A27: Barreau de Luxembourg (Bar Association) | B27: Federation | C27: Medium-High | D27: Researching | E27: Research Barreau CPD program; check if pension/social-security topic qualifies for CLE points | F27: Legal professional access, CPD channel, cross-border expertise community | G27: Luxembourg Bar Association with 3,250 members; very international — EU lawyers can register under home-country title. Major international law firms (A&O, Clifford Chance, etc.) have LU offices. Lawyers require 16 CPD points/year. Many cross-border practitioners. | H27: Access to 3,250 legal professionals, many internationally mobile; CPD requirement creates event attendance; cross-border lawyers face pension fragmentation between home country and LU | I27: Lawyers with international careers across multiple jurisdictions have pension rights scattered in each country they've practiced. We help them track and organize those rights. | J27: CPD session / conference / member information | K27: Statutory professional body; mandatory membership; runs CPD program; more regulatory than networking-focused | L27: 3,250-member reach, CPD training program, professional directory, disciplinary authority | M27: CPD-eligible session on cross-border pension rights for legal practitioners, practical guide for international lawyers in LU | O27: Whether pension/financial topic qualifies for CPD points; whether external speakers can propose sessions; contact at Bar Council
A28: OEC – Ordre des Experts-Comptables | B28: Federation | C28: Medium-High | D28: Researching | E28: Contact OEC; explore whether cross-border pension/tax topic fits their CPD program (60 credits/3 years) | F28: Accountancy professional access, CPD channel, fund-industry link, tax/pension expertise community | G28: Professional order for 1,168 chartered accountants and 553 firms in Luxembourg; mandatory membership. Many serve the fund industry (€3.5T+ AUM) and international corporate structures. EU-qualified accountants can practice in LU under mutual recognition — highly international workforce. | H28: Access to 1,168 accountants who advise international clients on tax/financial structures; CPD requirement (60 credits/3 years) creates captive training audience; direct link to fund industry | I28: Chartered accountants advise internationally mobile clients and employers on tax and financial planning. Cross-border pension rights are a natural extension of that advice. | J28: CPD session / training content / professional development | K28: Mandatory professional order; CPD program with training partnerships; co-located at 14 rue Erasme | L28: 1,168-member reach, CPD training program, peer review system, Accountancy Europe membership, fund industry connection | M28: CPD-eligible session on cross-border pension rights for accountants, practical guide for advising internationally mobile clients, tax-pension integration content | O28: Whether external CPD content proposals are accepted; contact at OEC secretariat

Sheet Ring 2 — Communities
A1: Organization | B1: Country Link | C1: Category | D1: Priority | E1: Status | F1: Next Action | G1: GTM Role | H1: Why They Care | I1: Our Interest | J1: Main Message | K1: Partnership Type | L1: Access Conditions | M1: Support They Can Offer | N1: What We Offer | O1: Contact Person | P1: Need to Confirm
A2: AMCHAM Luxembourg | B2: US / EN-speaking | C2: Country Community | D2: High | E2: Researching | F2: Check AMCHAM events calendar; explore committee membership or speaker opportunity | G2: Employer reach, expat events, committees | H2: We offer relevant member value for international companies and international employees; fits their information/problem-solving role | I2: Reach English-speaking employers, expat professionals, HR contacts, and member companies through events and committees | J2: We help international professionals and employers navigate fragmented pension rights built across Europe | K2: Event / employer pilot / content / committee discussion | L2: Likely member-driven; collaboration may depend on format or sponsorship | M2: Member events, employer visibility, committee access, newsletters | N2: Educational session, employer-benefit angle, guide, sharing news on changes in pension rights. | O2: Daniel McKenzie — Head of Communications, Events and Committee Structures — daniel@amcham.lu | P2: Whether speaking or content visibility needs membership or sponsor status or can start as external expert contribution
A3: British Chamber of Commerce | B3: UK / EN-speaking | C3: Country Community | D3: High | E3: Researching | F3: Contact BCC events team; propose pension-rights session for British expats in LU | G3: Expat events, employer reach, referrals | H3: We offer relevant member value for international companies and international employees; fits their event-based knowledge sharing | I3: Reach English-speaking employers, expat professionals, HR contacts, and member companies through events and committees | J3: We help international professionals and employers navigate fragmented pension rights built across Europe | K3: Event / content / community pilot / referrals | L3: Likely member-driven; collaboration may depend on format or sponsorship | M3: Community access, Events, business forums, member network | N3: Educational session, employer-benefit angle, guide, sharing news on changes in pension rights. | O3: Rebecca Kellagher — Manager — rebecca.kellagher@bcc.lu | P3: Whether speaking or content visibility needs membership or sponsor status or can start as external expert contribution
A4: CCIPL / Portugal–Luxembourg Chamber (ccill.lu) | B4: PT | C4: Country Association | D4: High | E4: Researching | F4: Contact CCIPL; propose pension workshop for Portuguese community in LU | G4: PT community reach, events, referrals | H4: Highly relevant member/community topic for Portugal-linked entrepreneurs and professionals; fits their business support and matchmaking role | I4: Reach Portugal-linked founders, professionals, firms, and their event/newsletter audience | J4: We help Portugal–Luxembourg professionals understand and organize pension rights across countries | K4: Event / content / community pilot / referrals | L4: Likely member-driven; collaboration may depend on format or sponsorship | M4: Community access, events, business introductions, newsletter potential, visibility | N4: Portugal–Luxembourg pension session, guide, pilot | O4: info@ccill.lu | P4: Whether speaking or content visibility needs membership or sponsor status or can start as external expert contribution
A5: Luxembourg-Poland Chamber of Commerce (LPCC) (lpcc.lu) | B5: PL | C5: Country Association | D5: Medium-High | E5: Researching | F5: Contact LPCC; explore joint event on pension rights for Polish professionals in LU | G5: PL community reach, events, referrals | H5: Relevant member/community topic for Poland-linked entrepreneurs and professionals; fits their business support and matchmaking role | I5: Reach Poland-linked founders, professionals, firms, and their event/newsletter audience | J5: We help internationally mobile professionals with Poland-linked careers organize pension rights across countries | K5: Event / content / community pilot / referrals | L5: Likely member-driven; collaboration may depend on format or sponsorship | M5: Community access, events, business introductions, newsletter potential, visibility | N5: Poland–Lux session, guide, pilot group | O5: Oliwia Gertych — Digital Marketer & Project Manager — oliwia.gertych@lpcc.lu | P5: Whether speaking or content visibility needs membership or sponsor status or can start as external expert contribution
A6: Official Spanish Chamber of Commerce in Belgium and Luxembourg (e-camara.com) | B6: ES | C6: Country Association | D6: Medium-High | E6: Researching | F6: Research Spanish Chamber events; identify contact for partnership proposal | G6: ES community reach, events, referrals | H6: Relevant member/community topic for Spain-linked entrepreneurs and professionals; fits their business support and matchmaking role | I6: Reach Spain-linked founders, professionals, firms, and their event/newsletter audience | J6: We help internationally mobile professionals with Spain-linked careers organize pension rights across countries | K6: Event / content / community pilot / referrals | L6: Likely member-driven; collaboration may depend on format or sponsorship (direct contact?) | M6: Community access, events, business introductions, newsletter potential, visibility | N6: Spain–Lux session, guide, pilot group | O6: luxemburgo@e-camara.com | P6: Whether speaking or content visibility needs membership or sponsor status or can start as external expert contribution
A7: Luxembourg-Italian Chamber of Commerce | B7: IT | C7: Country Association | D7: High | E7: Researching | F7: Contact Italian Chamber; propose pension-rights session for Italian professionals | G7: IT community reach, events, referrals | H7: Relevant topic for Italy-linked companies and professionals in Luxembourg, especially since Italy is one of our product expansion markets | I7: Reach Italy-linked founders, professionals, firms, and their event/newsletter audience | J7: We help Italy–Luxembourg professionals understand and organize pension rights across countries | K7: Event / content / community pilot / referrals | L7: Likely chamber-based; direct outreach possible | M7: Bilateral network, events, visibility, member access | N7: Italy–Lux pension education session, practical guide, pilot audience | O7: Luisa Castelli — Secrétaire général / Directeur — l.castelli@ccil.lu | P7: Whether speaking or content visibility needs membership or sponsor status or can start as external expert contribution
A8: CCI France Luxembourg | B8: FR | C8: Country Association | D8: High | E8: Researching | F8: Contact CCI France; explore cross-border pension content for French community | G8: FR community reach, events, credibility | H8: Highly relevant member/community topic for France-linked entrepreneurs and professionals; fits their business support and matchmaking role | I8: Reach France-linked founders, professionals, firms, and their event/newsletter audience; strong credibility in the France–Lux corridor | J8: We help internationally mobile professionals with France-linked careers organize pension rights across countries | K8: Event / content / community pilot / referrals | L8: Clear membership model and business club logic; first contact open, deeper visibility likely easier through partnership or member-style collaboration | M8: Community access, events, business introductions, newsletter potential, visibility | N8: France–Lux pension session, practical guide, employer-facing content, pilot | O8: Alexandra Benel, Director — alexandra.benel@cfci.lu; general cfci@cfci.lu | P8: Whether speaking or content visibility needs membership or sponsor status or can start as external expert contribution
A9: Business Club Luxemburg-Schweiz | B9: CH | C9: Country Association | D9: Low | E9: Researching | F9: Research Swiss Club events; check if pension topic fits their networking format | G9: CH community reach, cross-border events | H9: Highly relevant member/community topic for Switzerland-linked entrepreneurs and professionals; fits their business support and matchmaking role | I9: Reach Switzerland-linked founders, professionals, firms, and their event/newsletter audience | J9: We help Switzerland–Luxembourg professionals bring clarity to fragmented pension rights and occupational/private retirement assets across countries | K9: Event / content / community pilot / referrals | L9: Accredited bilateral business club, but detailed public access conditions need confirmation through direct contact via Chamber bilateral route | M9: Community access, events, business introductions, newsletter potential, visibility | N9: Swiss–Lux pension education session, practical cross-border guide, pilot audience | P9: Whether speaking or content visibility needs membership or sponsor status or can start as external expert contribution
A10: Business Club Belgium-Luxembourg (BCBL) | B10: BE | C10: Country Association | D10: High | E10: Researching | F10: Contact BCBL; propose pension-rights session for Belgian professionals in LU | G10: BE community reach, events, referrals | H10: Highly relevant member/community topic for France-linked entrepreneurs and professionals; fits their business support and matchmaking role | I10: Reach Belgian-linked companies, professionals, firms, and their event/newsletter audience | J10: We help internationally mobile professionals with Belgium-linked careers organize pension rights across countries | K10: Event / content / community pilot / referrals | L10: Appears to be member-based business club; first contact open; deeper collaboration likely depends on club format or membership/sponsorship | M10: Community access, events, business introductions, newsletter potential, visibility | N10: Belgium–Lux pension session, practical guide, pilot group, employer-facing content | O10: contact@bcbl.be | P10: Whether speaking or content visibility needs membership or sponsor status or can start as external expert contribution
A11: AHK debelux – German-Belgian-Luxembourg Chamber of Commerce | B11: DE | C11: Country Association | D11: High | E11: Researching | F11: Check if AHK debelux has a LU-specific working group or events; identify contact for partnership | G11: German community employer access, cross-border worker channel | H11: ~12,700 Germans resident in LU + ~50,000 daily cross-border commuters from DE; pension fragmentation between DE and LU social security systems is extremely common | I11: Access German employers and cross-border professionals in LU; high pension-relevance given DE-LU commuter flows | J11: We help employers and cross-border professionals between Germany and Luxembourg organize fragmented pension rights across both systems | K11: Employer pilot / event / cross-border content | L11: Bilateral chamber established since 1894; open to collaboration via events and seminars | M11: Events, employer network, cross-border employer access, B2B intros, seminar channel | N11: Cross-border pension guide, DE-LU employer session, practical content for German professionals in LU | P11: Whether they have Luxembourg-specific events; best contact for partnership proposals
A12: ROMLUX – Romania Luxemburg Business Forum | B12: RO | C12: Country Association | D12: High | E12: Researching | F12: Contact via website; propose educational session on pension rights for Romanian professionals in LU | G12: Romanian community access, startup/tech channel, cultural bridge | H12: ~6,500 Romanians in LU (1% of population, top-10 nationality), fast-growing community; many young professionals in finance and tech with fragmented pension rights between RO and LU | I12: Reach Romanian professionals and entrepreneurs in Luxembourg; growing community with strong pension-fragmentation relevance | J12: We help Romanian professionals in Luxembourg understand and organize pension rights built across Romania, Luxembourg and other EU countries | K12: Event / community content / networking partnership | L12: Accredited bilateral chamber; 177 members; very active events calendar; partners with BCC, CC, Luxinnovation | M12: Community events, networking, business directory access, startup channel, cultural events | N12: Pension-rights workshop for Romanian professionals, practical EU pension guide, pilot audience | P12: Whether they host educational sessions; best contact for partnership discussions
A13: NOBELUX – Nordic Chamber of Commerce | B13: Nordic | C13: Country Association | D13: Medium-High | E13: Researching | F13: Contact NOBELUX; explore whether pension topic fits their events or member services | G13: Nordic finance professional access, high-income expat community, FinTech network | H13: ~7,200 Nordic/Baltic residents in LU; mostly high-income finance and EU-institution professionals with careers spanning Scandinavia, UK, and continental Europe. Nordic pension systems are strong but fragmented across countries. | I13: Reach Nordic professionals in Luxembourg's finance sector; high-value audience with pension rights split across Nordic and EU systems | J13: Nordic professionals working in Luxembourg have pension rights in Scandinavian systems (strong but different from each other and from LU). We help them consolidate the picture across all countries. | K13: Event / FinTech pavilion / networking / member content | L13: Independent membership org; covers DK, FI, IS, NO, SE; events incl. FinTech pavilions; business networking | M13: Business networking events, FinTech pavilions, bilateral trade events, member communications | N13: Pension-portability session for Nordic expats, practical guide for Scandinavian professionals in LU, FinTech-pension angle | P13: Whether they host educational content; best contact for partnership; FinTech angle vs general events

Sheet Ring 3 — Abroad (Stage 2)
A1: Organization | B1: Country | C1: Category | D1: Priority | E1: Status | F1: Next Action | G1: GTM Role | H1: Why They Care | I1: Our Interest | J1: Main Message | K1: Partnership Type | L1: Access Conditions | M1: Support They Can Offer | N1: What We Offer | O1: Contact Person | P1: Need to Confirm
B2: FR
B3: IT
B4: PT
B5: BE
B6: DE
B7: ES

Sheet Action Plan
A1: Ring | B1: Organization | C1: Country / Community | D1: Type of Organization | E1: Original Category | F1: Current Priority | G1: Contact Access | H1: Credibility Power | I1: Customer Reach Potential | J1: Market Expansion Value | K1: Strategic Route | L1: Recommended Timing | M1: Primary Goal | N1: First Ask | O1: Main Message | P1: Why They Care | Q1: Our Interest | R1: Partnership Type | S1: Access Conditions | T1: Support They Can Offer | U1: What We Offer | V1: Contact Person | W1: Next Action | X1: Status | Y1: Need to Confirm
A2: Ring 1 | B2: Luxinnovation | C2: Luxembourg-wide | D2: Hub / Public / Ecosystem | E2: Hub / Public Body | F2: Medium-High | G2: Direct contact | H2: 5 | I2: 2 | J2: 3 | K2: Credibility-first | L2: Weeks 3–6 | M2: Secure logo / trust signal and warm intros before broad outreach | N2: Intro meeting + co-branded educational format | O2: We are building a retirement-rights solution for internationally mobile professionals and employers | P2: Relevant if they see us as an innovation/startup project with partner-finding and market-launch potential | Q2: Reach startup ecosystem, innovation partners, and scaling-support structures through their startup and partner-finding support | R2: Innovation support / partner finding / scaling support | S2: Mission-based support for innovation projects | T2: Partner finding, startup support, market-launch preparation, funding orientation | U2: Innovation case, ecosystem contribution, pilot | V2: Inna Perepelytsya — Senior Advisor — inna.perepelytsya@luxinnovation.lu Sven Baltes — Manager – Startup Relations — sven.baltes@luxinnovation.lu | W2: Explore Fit 4 Start or partner program; check if pension topic fits their innovation support | X2: Researching | Y2: Whether they see the project as strong enough innovation fit
A3: Ring 1 | B3: LPEA – Luxembourg Private Equity & Venture Capital Association | C3: Luxembourg-wide | D3: Association / Federation / Professional body | E3: Federation | F3: Medium-High | G3: Direct contact | H3: 4 | I3: 3 | J3: 2 | K3: Mixed | L3: Weeks 3–6 | M3: Test fit, visibility, and targeted user acquisition | N3: Exploratory call to identify best collaboration format | O3: We help internationally mobile professionals and employers in finance understand and organize fragmented pension rights across countries. | P3: Our solution is relevant to an international finance audience with highly mobile careers; LPEA's mission is to connect, inform, and represent the PE/VC ecosystem. | Q3: Reach PE/VC firms, private banks, family offices, advisors, and highly international professionals; gain premium finance visibility and potential employer-level access. | R3: Event / thought leadership / employer pilot / finance-community content | S3: Clear membership-based association, but direct contact is open. | T3: Events, network access, industry visibility, premium-segment credibility, knowledge-sharing platform. | U3: Finance-focused educational session, premium professional guide, pilot group, thought leadership content. | V3: Claus Mansfeldt — President — claus.mansfeldt@lpea.lu Stephane Pesch — CEO — stephane.pesch@lpea.lu Johann Herz — Head of Events & Communication — johann.herz@lpea.lu | W3: Research LPEA events calendar; propose PE/VC-angle session on founder pension complexity | X3: Researching | Y3: Whether non-members can speak, publish, or co-host; best operational contact beyond general office.
A4: Ring 1 | B4: Luxembourg for Finance (LFF) | C4: Luxembourg-wide | D4: Hub / Public / Ecosystem | E4: Hub / Public Body | F4: Medium-High | G4: Direct contact | H4: 4 | I4: 3 | J4: 2 | K4: Mixed | L4: Weeks 3–6 | M4: Test fit, visibility, and targeted user acquisition | N4: Exploratory call to identify best collaboration format | O4: We help employers support internationally mobile employees facing fragmented pension rights across countries | P4: Strong fit for the international-finance and international-talent angle; your topic is relevant for globally mobile finance professionals | Q4: Reach international finance audience, institutions, and financial-ecosystem visibility | R4: Event / ecosystem intro / thought leadership / visibility | S4: Likely institutional and fit-driven | T4: Visibility, finance-community access, ecosystem introductions | U4: Finance-professional guide, panel topic, educational session | V4: Jonathan Westhead — Head of Communications — jonathan.westhead@lff.lu | W4: Contact LFF team; explore thought-leadership content on pension portability for finance sector | X4: Researching | Y4: Whether they would host or circulate a topic like this
A5: Ring 2 | B5: Luxembourg-Poland Chamber of Commerce (LPCC) (lpcc.lu) | C5: PL | D5: Country / Bilateral Chamber | E5: Country Association | F5: Medium-High | G5: Direct contact | H5: 3 | I5: 3 | J5: 3 | K5: Lower-priority community reach (defer) | L5: Later / not in current expansion-priority list | M5: Test fit, visibility, and targeted user acquisition | N5: Exploratory call to identify best collaboration format | O5: We help internationally mobile professionals with Poland-linked careers organize pension rights across countries | P5: Relevant member/community topic for Poland-linked entrepreneurs and professionals; fits their business support and matchmaking role | Q5: Reach Poland-linked founders, professionals, firms, and their event/newsletter audience | R5: Event / content / community pilot / referrals | S5: Likely member-driven; collaboration may depend on format or sponsorship | T5: Community access, events, business introductions, newsletter potential, visibility | U5: Poland–Lux session, guide, pilot group | V5: Oliwia Gertych — Digital Marketer & Project Manager — oliwia.gertych@lpcc.lu | W5: Keep warm only; no active outreach until Poland becomes a priority corridor | X5: Researching | Y5: Whether speaking or content visibility needs membership or sponsor status or can start as external expert contribution
A6: Ring 1 | B6: ALFI – Association of the Luxembourg Fund Industry | C6: Luxembourg-wide | D6: Association / Federation / Professional body | E6: Federation | F6: Medium-High | G6: No contact | H6: 4 | I6: 3 | J6: 2 | K6: Mixed | L6: Weeks 3–6 | M6: Test fit, visibility, and targeted user acquisition | N6: Exploratory call to identify best collaboration format | O6: We help employers support internationally mobile employees facing fragmented pension rights across countries | P6: Relevant if positioned around international finance professionals, mobility, and long-term retirement/wealth-planning literacy | Q6: Reach international finance professionals, member firms, and industry visibility in Luxembourg finance ecosystem | R6: Thought leadership / event / finance-community content | S6: Likely member-driven and industry-focused | T6: Events, premium visibility, finance-network access | U6: Educational session, finance-focused guide, premium pilot audience | W6: Check ALFI event calendar; propose educational session on pension rights for fund professionals | X6: Researching | Y6: Whether they would see this as relevant beyond investment/fund topics
A7: Ring 1 | B7: Barreau de Luxembourg (Bar Association) | C7: Luxembourg-wide | D7: Association / Federation / Professional body | E7: Federation | F7: Medium-High | G7: No contact | H7: 4 | I7: 3 | J7: 1 | K7: Mixed | L7: Weeks 3–6 | M7: Test fit, visibility, and targeted user acquisition | N7: Exploratory call to identify best collaboration format | O7: Lawyers with international careers across multiple jurisdictions have pension rights scattered in each country they've practiced. We help them track and organize those rights. | P7: Luxembourg Bar Association with 3,250 members; very international — EU lawyers can register under home-country title. Major international law firms (A&O, Clifford Chance, etc.) have LU offices. Lawyers require 16 CPD points/year. Many cross-border practitioners. | Q7: Access to 3,250 legal professionals, many internationally mobile; CPD requirement creates event attendance; cross-border lawyers face pension fragmentation between home country and LU | R7: CPD session / conference / member information | S7: Statutory professional body; mandatory membership; runs CPD program; more regulatory than networking-focused | T7: 3,250-member reach, CPD training program, professional directory, disciplinary authority | U7: CPD-eligible session on cross-border pension rights for legal practitioners, practical guide for international lawyers in LU | W7: Research Barreau CPD program; check if pension/social-security topic qualifies for CLE points | X7: Researching | Y7: Whether pension/financial topic qualifies for CPD points; whether external speakers can propose sessions; contact at Bar Council
A8: Ring 1 | B8: OEC – Ordre des Experts-Comptables | C8: Luxembourg-wide | D8: Association / Federation / Professional body | E8: Federation | F8: Medium-High | G8: No contact | H8: 4 | I8: 3 | J8: 1 | K8: Mixed | L8: Weeks 3–6 | M8: Test fit, visibility, and targeted user acquisition | N8: Exploratory call to identify best collaboration format | O8: Chartered accountants advise internationally mobile clients and employers on tax and financial planning. Cross-border pension rights are a natural extension of that advice. | P8: Professional order for 1,168 chartered accountants and 553 firms in Luxembourg; mandatory membership. Many serve the fund industry (€3.5T+ AUM) and international corporate structures. EU-qualified accountants can practice in LU under mutual recognition — highly international workforce. | Q8: Access to 1,168 accountants who advise international clients on tax/financial structures; CPD requirement (60 credits/3 years) creates captive training audience; direct link to fund industry | R8: CPD session / training content / professional development | S8: Mandatory professional order; CPD program with training partnerships; co-located at 14 rue Erasme | T8: 1,168-member reach, CPD training program, peer review system, Accountancy Europe membership, fund industry connection | U8: CPD-eligible session on cross-border pension rights for accountants, practical guide for advising internationally mobile clients, tax-pension integration content | W8: Contact OEC; explore whether cross-border pension/tax topic fits their CPD program (60 credits/3 years) | X8: Researching | Y8: Whether external CPD content proposals are accepted; contact at OEC secretariat
A9: Ring 1 | B9: Technoport | C9: Luxembourg-wide | D9: Hub / Public / Ecosystem | E9: Hub / Public Body | F9: Medium-High | G9: No contact | H9: 4 | I9: 3 | J9: 1 | K9: Mixed | L9: Weeks 3–6 | M9: Test fit, visibility, and targeted user acquisition | N9: Exploratory call to identify best collaboration format | O9: We help founders and startup talent with international careers get clarity on fragmented pension rights | P9: National technology incubator; often the first local hub for international startups arriving in Luxembourg — these founders face immediate cross-border pension fragmentation | Q9: Reach international tech founders at the moment they relocate to Luxembourg; pilot-user access and ecosystem credibility | R9: Workshop / pilot / ecosystem intro / content | S9: Public incubator; likely mission-based and open to collaboration | T9: International-founder community, event channel, ecosystem credibility, early-stage access | U9: Founder pension workshop, relocation guide for international startups, pilot session | W9: Contact via website; check if they run community events for resident startups | X9: Researching | Y9: Whether they run community programming; best contact for workshop/content proposals
A10: Ring 1 | B10: ILAC – Institut Luxembourgeois des Actuaires | C10: Luxembourg-wide | D10: Association / Federation / Professional body | E10: Federation | F10: Medium-High | G10: No contact | H10: 4 | I10: 2 | J10: 1 | K10: Mixed | L10: Weeks 3–6 | M10: Test fit, visibility, and targeted user acquisition | N10: Exploratory call to identify best collaboration format | O10: Actuaries understand cross-border pension complexity better than anyone. We give their clients the tools to navigate it. | P10: Institute of ~300 actuaries active in Luxembourg since 1992; actuaries are pension specialists by profession — they design and value the pension products that internationally mobile workers accumulate across countries | Q10: Access to 300 pension/insurance specialists; natural amplifiers who understand the technical complexity; conferences attract 150+ professionals | R10: Conference session / technical partnership / CPD content | S10: Professional institute; regular open conferences; CPD program for members | T10: Actuarial conferences, CPD program, technical community, Actuview platform partnership | U10: Cross-border pension data/insight session for actuaries, CPD-eligible content, technical partnership | W10: Contact ILAC bureau; propose actuarial-angle session on cross-border pension portability | X10: Researching | Y10: Whether CPD session proposals are open; best contact at ILAC bureau
A11: Ring 2 | B11: NOBELUX – Nordic Chamber of Commerce | C11: Nordic | D11: Country / Bilateral Chamber | E11: Country Association | F11: Medium-High | G11: No contact | H11: 3 | I11: 3 | J11: 3 | K11: Lower-priority community reach (defer) | L11: Later / not in current expansion-priority list | M11: Test fit, visibility, and targeted user acquisition | N11: Exploratory call to identify best collaboration format | O11: Nordic professionals working in Luxembourg have pension rights in Scandinavian systems (strong but different from each other and from LU). We help them consolidate the picture across all countries. | P11: ~7,200 Nordic/Baltic residents in LU; mostly high-income finance and EU-institution professionals with careers spanning Scandinavia, UK, and continental Europe. Nordic pension systems are strong but fragmented across countries. | Q11: Reach Nordic professionals in Luxembourg's finance sector; high-value audience with pension rights split across Nordic and EU systems | R11: Event / FinTech pavilion / networking / member content | S11: Independent membership org; covers DK, FI, IS, NO, SE; events incl. FinTech pavilions; business networking | T11: Business networking events, FinTech pavilions, bilateral trade events, member communications | U11: Pension-portability session for Nordic expats, practical guide for Scandinavian professionals in LU, FinTech-pension angle | W11: Keep in backlog; not tied to current launch/expansion sequence | X11: Researching | Y11: Whether they host educational content; best contact for partnership; FinTech angle vs general events
A12: Ring 1 | B12: Luxembourg-City Incubator (LCI) | C12: Luxembourg-wide | D12: Hub / Public / Ecosystem | E12: Hub / Public Body | F12: Medium-High | G12: No contact | H12: 3 | I12: 2 | J12: 1 | K12: Mixed | L12: Weeks 3–6 | M12: Test fit, visibility, and targeted user acquisition | N12: Exploratory call to identify best collaboration format | O12: We help founders and startup talent with international careers get clarity on fragmented pension rights | P12: City-backed incubator for early-stage companies; many incubated founders are internationally mobile and face cross-border pension complexity | Q12: Access to international startup founders as pilot users; visibility in the incubator ecosystem; complementary channel to HoST | R12: Workshop / pilot / ecosystem intro | S12: Backed by City of Luxembourg and Chamber of Commerce; likely mission-based, open to collaboration | T12: Startup-founder access, event channel, incubator community, pilot audience | U12: Founder pension workshop, practical guide, pilot session for incubated startups | W12: Contact via HoST or directly; check if incubated startups fit as pilot audience | X12: Researching | Y12: Whether collaboration needs to go through HoST or can be direct; best contact for event/workshop proposals
A13: Ring 1 | B13: Luxembourg Chamber of Commerce (cc.lu) | C13: Luxembourg-wide | D13: Chamber | E13: Chamber | F13: High | G13: Direct contact | H13: 5 | I13: 4 | J13: 3 | K13: Credibility-first | L13: Weeks 1–3 | M13: Secure logo / trust signal and warm intros before broad outreach | N13: Intro meeting + co-branded educational format | O13: We help employers and internationally mobile professionals with international careers understand and organize pension rights across countries | P13: Better support offer for member companies and internationally active businesses | Q13: Reach employers, SMEs, and international business members via Chamber channels, events, and International Affairs | R13: Event / B2B intro / content / referral | S13: Core contact is open; deeper visibility may depend on Chamber process or membership context | T13: Intros, event route, international business access | U13: Employer-facing content, pilot, educational session | V13: Amrita Singh — Matchmaking Coordinator, International Affairs — amrita.singh@cc.lu | W13: Check CC events calendar; explore membership or partnership application route | X13: Researching | Y13: Whether access to member-facing formats needs extra conditions
A14: Ring 1 | B14: House of Entrepreneurship | C14: Luxembourg-wide | D14: Hub / Public / Ecosystem | E14: Hub / Public Body | F14: High | G14: General contact | H14: 5 | I14: 4 | J14: 2 | K14: Credibility-first | L14: Weeks 1–3 | M14: Secure logo / trust signal and warm intros before broad outreach | N14: Intro meeting + co-branded educational format | O14: We help employers and internationally mobile professionals with international careers understand and organize pension rights across countries | P14: We offer useful value-add for people with international careers; fits their mission to inform, guide, and connect entrepreneurs | Q14: Access to founders and internationally mobile entrepreneurs through workshops and advisor referrals; visibility in the entrepreneurship ecosystem; practical support and ecosystem introductions. | R14: Workshop / content / pilot / ecosystem intro | S14: Likely mission-based, free first contact; no public membership requirement found | T14: Advisor meeting, workshop opportunity, intros, feedback | U14: Workshop, guide, pilot session | V14: info@houseofentrepreneurship.lu | W14: Identify contact at House of Entrepreneurship; check upcoming startup events to attend | X14: Researching | Y14: Whether formal promotion or repeated collaboration needs separate arrangement
A15: Ring 1 | B15: Luxembourg Employers' Association (UEL) | C15: Luxembourg-wide | D15: Association / Federation / Professional body | E15: Federation | F15: High | G15: General contact | H15: 5 | I15: 4 | J15: 2 | K15: Credibility-first | L15: Weeks 1–3 | M15: Secure logo / trust signal and warm intros before broad outreach | N15: Intro meeting + co-branded educational format | O15: We help employers support internationally mobile employees facing fragmented pension rights across countries | P15: Our solution can support employers dealing with internationally mobile employees and long-term employee wellbeing topics | Q15: Reach employers, business leaders, and employer associations; strong B2B credibility and policy-level visibility | R15: Employer pilot / policy discussion / event / content | S15: Likely institutional and selective; contact possible through public route | T15: Employer credibility, possible introductions, policy/business visibility | U15: Employer-benefit angle, educational content, pilot idea | V15: Jean-Paul Olinger / public route press@uel.lu | W15: Research UEL employer events; identify contact for employer-facing pension content | X15: Researching | Y15: Best operational contact and whether topic fits their agenda
A16: Ring 2 | B16: CCI France Luxembourg | C16: FR | D16: Country / Bilateral Chamber | E16: Country Association | F16: High | G16: General contact | H16: 5 | I16: 5 | J16: 5 | K16: Customer reach first | L16: Weeks 1–3 | M16: Access target users and community sign-ups in Luxembourg | N16: Webinar / event / newsletter feature for the target community | O16: We help internationally mobile professionals with France-linked careers organize pension rights across countries | P16: Highly relevant member/community topic for France-linked entrepreneurs and professionals; fits their business support and matchmaking role | Q16: Reach France-linked founders, professionals, firms, and their event/newsletter audience; strong credibility in the France–Lux corridor | R16: Event / content / community pilot / referrals | S16: Clear membership model and business club logic; first contact open, deeper visibility likely easier through partnership or member-style collaboration | T16: Community access, events, business introductions, newsletter potential, visibility | U16: France–Lux pension session, practical guide, employer-facing content, pilot | V16: Alexandra Benel, Director — alexandra.benel@cfci.lu; general cfci@cfci.lu | W16: Start outreach in Weeks 1–3; propose early France-linked community session tied to launch countries | X16: Researching | Y16: Whether speaking or content visibility needs membership or sponsor status or can start as external expert contribution
A17: Ring 1 | B17: LHoFT | C17: Luxembourg-wide | D17: Hub / Public / Ecosystem | E17: Hub / Public Body | F17: High | G17: No contact | H17: 5 | I17: 3 | J17: 3 | K17: Credibility-first | L17: Weeks 1–3 | M17: Secure logo / trust signal and warm intros before broad outreach | N17: Intro meeting + co-branded educational format | O17: We are building a retirement-rights solution for internationally mobile professionals and employers | P17: Strong fintech / wealthtech / employee-financial-wellbeing angle; relevant to financial innovation and ecosystem collaboration | Q17: Access to fintech, employers, and innovation partners; strong ecosystem visibility and credibility; support through introductions and pilot discussions. | R17: Fintech partnership / pilot / ecosystem intro / employer-benefit discussion | S17: Likely selective and fit-driven | T17: Ecosystem credibility, intros, pilot conversations, event route | U17: Fintech use case, thought leadership, pilot, validation insights | W17: Contact LHoFT team; propose fintech-meets-pension session for resident startups | X17: Researching | Y17: Whether membership/incubation is needed for deeper support
A18: Ring 1 | B18: ABBL – Luxembourg Bankers' Association | C18: Luxembourg-wide | D18: Association / Federation / Professional body | E18: Federation | F18: High | G18: No contact | H18: 5 | I18: 4 | J18: 2 | K18: Credibility-first | L18: Weeks 1–3 | M18: Secure logo / trust signal and warm intros before broad outreach | N18: Intro meeting + co-branded educational format | O18: We help employers and internationally mobile professionals in finance understand and organize fragmented pension rights across countries | P18: Largest financial-sector association; many member banks employ highly mobile international professionals whose pension rights fragment across countries | Q18: Reach banks, financial intermediaries, and their internationally mobile employees; gain premium financial-sector credibility and employer-level access | R18: Employer pilot / event / thought leadership / finance-community content | S18: Member-driven association; first contact open via public route | T18: Events, employer network, finance-sector visibility, working-group access, premium credibility | U18: Finance-professional pension guide, employer-facing educational session, pilot audience, thought leadership content | W18: Research contact route; check if ABBL has HR / mobility working group | X18: Researching | Y18: Best operational contact; whether topic fits their employer/HR agenda or innovation working group
A19: Ring 2 | B19: Business Club Luxemburg-Schweiz | C19: CH | D19: Country / Bilateral Chamber | E19: Country Association | F19: Low | G19: No contact | H19: 3 | I19: 2 | J19: 5 | K19: Credibility + expansion bridge | L19: Weeks 1–3 | M19: Build corridor bridge for France / PT / IT / BE / DE / CH expansion | N19: Bilateral-community event and cross-country visibility | O19: We help Switzerland–Luxembourg professionals bring clarity to fragmented pension rights and occupational/private retirement assets across countries | P19: Highly relevant member/community topic for Switzerland-linked entrepreneurs and professionals; fits their business support and matchmaking role | Q19: Reach Switzerland-linked founders, professionals, firms, and their event/newsletter audience | R19: Event / content / community pilot / referrals | S19: Accredited bilateral business club, but detailed public access conditions need confirmation through direct contact via Chamber bilateral route | T19: Community access, events, business introductions, newsletter potential, visibility | U19: Swiss–Lux pension education session, practical cross-border guide, pilot audience | W19: Start outreach in Weeks 1–3; use Swiss-linked angle for early credibility and launch-country alignment | X19: Researching | Y19: Whether speaking or content visibility needs membership or sponsor status or can start as external expert contribution
A20: Ring 1 | B20: Maison Moderne / Paperjam / Delano | C20: Luxembourg-wide | D20: Media | E20: Media | F20: High | G20: Direct contact | H20: 5 | I20: 4 | J20: 1 | K20: Credibility-first | L20: Weeks 2–4 | M20: Secure logo / trust signal and warm intros before broad outreach | N20: Intro meeting + co-branded educational format | O20: We are building a retirement-rights solution for internationally mobile professionals and employers | P20: Strong editorial relevance if framed as international talent, retirement fragmentation, and employer/expat financial clarity in Luxembourg | Q20: Reach business audience, employers, decision-makers, and broad Luxembourg visibility through media exposure | R20: Media / thought leadership / interview / article | S20: Editorial fit required; not a classic partnership | T20: Visibility, credibility, audience reach, story amplification | U20: Article angle, expert commentary, ecosystem story | V20: Aaron Grunwald — Editor-in-chief at Delano — aaron.grunwald@maisonmoderne.com Thierry Labro — Editor-in-chief at Delano — thierry.labro@maisonmoderne.com | W20: Research Paperjam/Delano editorial calendar; propose thought-leadership article or interview | X20: Researching | Y20: Best story angle: expat, talent, pensions, founder journey, or fintech
A21: Ring 1 | B21: ADEM – Agence pour le Développement de l'Emploi | C21: Luxembourg-wide | D21: Hub / Public / Ecosystem | E21: Hub / Public Body | F21: High | G21: No contact | H21: 5 | I21: 3 | J21: 1 | K21: Credibility-first | L21: Weeks 2-4 | M21: Secure logo / trust signal and warm intros before broad outreach | N21: Intro meeting + co-branded educational format | O21: We help internationally mobile professionals and employers understand and organize fragmented pension rights across countries | P21: Luxembourg's public employment agency; directly assists cross-border workers and expats with professional integration — pension and social security clarity is a natural extension | Q21: Reach internationally mobile jobseekers and employers through ADEM's integration services; public-sector credibility and visibility | R21: Information partnership / content / referral / workshop | S21: Public institution; contact open through official channels | T21: Expat integration reach, employer services access, public-sector referral channel, credibility | U21: Pension-rights information resource for expats, employer guide, educational content for integration services | W21: Research public contact route; explore if they have expat integration or employer-services team | X21: Researching | Y21: Whether they have an employer-services or expat-integration team; best contact route for partnerships
A22: Ring 1 | B22: HRCommunity.lu | C22: Luxembourg-wide | D22: HR network | E22: HR Network | F22: High | G22: No contact | H22: 4 | I22: 5 | J22: 1 | K22: Customer reach first | L22: Weeks 2–4 | M22: Access target users and community sign-ups in Luxembourg | N22: Webinar / event / newsletter feature for the target community | O22: We help HR professionals support internationally mobile employees facing fragmented pension rights across countries | P22: Reference HR community in Luxembourg since 1992; their member companies manage internationally mobile employees whose pension rights are a real HR pain point | Q22: Direct access to HR directors and people managers across all sectors; visibility as an expert solution for cross-border employee benefits | R22: Event / workshop / content / employer pilot | S22: Membership-based community of HR professionals; contact open through website | T22: HR-community events, employer network, sector-wide HR visibility, knowledge-sharing platform | U22: Cross-border pension workshop for HR teams, practical employer guide, pilot group, thought leadership | W22: Contact via website; propose educational session on cross-border pension rights for HR professionals | X22: Researching | Y22: Whether they host external expert sessions; best contact for partnership discussions
A23: Ring 1 | B23: FEDIL – The Voice of Luxembourg’s Industry | C23: Luxembourg-wide | D23: Association / Federation / Professional body | E23: Federation | F23: Medium-High | G23: No contact | H23: 4 | I23: 4 | J23: 2 | K23: B2B pilot | L23: Weeks 2–4 | M23: Open HR / employer pilot conversations and employee-benefit angle | N23: Short meeting on employee pilot or HR content collaboration | O23: We help employers support internationally mobile employees facing fragmented pension rights across countries | P23: Relevant for employers with international talent and cross-border workforce management needs | Q23: Reach industrial employers, HR/business leaders, and employer network visibility | R23: Employer pilot / event / content / referrals | S23: Likely association-based and agenda-driven | T23: Employer network, business visibility, sector reach | U23: Employer-facing workshop, international-workforce support angle | W23: Research FEDIL member events; identify HR/employer-services contact | X23: Researching | Y23: Best contact person and whether topic fits employer agenda
A24: Ring 1 | B24: House of Startups (HoST) | C24: Luxembourg-wide | D24: Hub / Public / Ecosystem | E24: Hub / Public Body | F24: High | G24: General contact | H24: 4 | I24: 4 | J24: 2 | K24: Mixed | L24: Weeks 8+ | M24: Test fit, visibility, and targeted user acquisition | N24: Exploratory call to identify best collaboration format | O24: We help founders and startup talent with international careers get clarity on fragmented pension rights | P24: We offer useful value-add for people with international careers; fits their mission to inform, guide, and connect entrepreneurs | Q24: Access to startup founders and startup employees; visibility in the startup ecosystem; pilot-user access and community support. | R24: Workshop / content / pilot / ecosystem intro | S24: Likely open for first contact; deeper activation may depend on ecosystem fit or resident status | T24: Startup-community access, pilot audience, event/community route | U24: Workshop, guide, pilot session | V24: reception@host.lu | W24: Contact HoST reception; ask about hosting a pension-rights workshop for startups | X24: Researching | Y24: Whether access to resident startups or event slots needs internal sponsor
A25: Ring 1 | B25: LBAN – Luxembourg Business Angel Network | C25: Luxembourg-wide | D25: Hub / Public / Ecosystem | E25: Hub / Public Body | F25: Medium | G25: General contact | H25: 3 | I25: 2 | J25: 1 | K25: Mixed | L25: Weeks 8+ | M25: Test fit, visibility, and targeted user acquisition | N25: Exploratory call to identify best collaboration format | O25: We help internationally mobile professionals and employers in finance understand and organize fragmented pension rights across countries. | P25: Relevant if we position the solution for founders, investors, and internationally mobile startup operators; LBAN's mission is to connect business angels with the entrepreneurial ecosystem and support startup growth. | Q25: Reach angel investors, founders, startup teams, and ecosystem actors; gain startup/investor visibility and possible intros to founder communities and early adopters. | R25: Event / startup-investor content / ecosystem intro / pilot | S25: Membership/network-based, but general contact is open. | T25: Investor/startup ecosystem visibility, founder access, event/network route, community credibility. | U25: Founder/investor education session, startup-team guide, pilot-user angle, ecosystem content. | V25: info@lban.lu; public contacts include Michel Rzonzef (President) and Teona Khubutia (Manager). | W25: Contact LBAN network manager; explore startup-founder pension workshop | X25: Researching | Y25: Whether they see the topic as relevant enough for members; whether event/content collaboration requires membership or sponsor route.
A26: Ring 1 | B26: Social Business Incubator (SBI) | C26: Luxembourg-wide | D26: Hub / Public / Ecosystem | E26: Hub / Public Body | F26: Medium | G26: General contact | H26: 2 | I26: 2 | J26: 1 | K26: Mixed | L26: Weeks 8+ | M26: Test fit, visibility, and targeted user acquisition | N26: Exploratory call to identify best collaboration format | O26: We want to improve long-term financial clarity and pension access for internationally mobile people | P26: If positioned as financial inclusion / long-term resilience for internationally mobile people, it fits their social-impact support logic | Q26: Reach social entrepreneurs, impact projects, and communities where financial clarity is part of social inclusion | R26: Impact partnership / workshop / ecosystem intro | S26: Likely mission-based support | T26: Advice, training, impact-network intros, social positioning | U26: Financial wellbeing / inclusion workshop, impact framing | V26: contact@sbi.lu | W26: Contact SBI; propose social-impact angle on financial inclusion for mobile workers | X26: Researching | Y26: Whether our project is impact-oriented enough for active support
A27: Ring 1 | B27: ACA – Association des Compagnies d'Assurances | C27: Luxembourg-wide | D27: Association / Federation / Professional body | E27: Federation | F27: High | G27: No contact | H27: 4 | I27: 3 | J27: 1 | K27: Mixed | L27: Weeks 8+ | M27: Test fit, visibility, and targeted user acquisition | N27: Exploratory call to identify best collaboration format | O27: We complement pillar 2-3 pension products by helping internationally mobile workers understand their fragmented pillar 1 rights across countries | P27: Professional association of 146 Luxembourg insurers and reinsurers; directly involved in government consultations on Luxembourg's public pension system and second/third pillar reform | Q27: Access to the insurance industry that designs and distributes pension products; partnership credibility on pension topics; visibility in policy discussions | R27: Content partnership / thought leadership / event / policy input | S27: Member-driven industry association; contact via ACA management | T27: Insurance industry network, pension policy access, events, working groups, House of Finance co-location with ABBL/ALFI/LFF | U27: Cross-border pension insight for insurance members, educational content for employers using pillar 2-3 products, thought leadership | W27: Contact ACA; explore pension/insurance pillar 2-3 content collaboration | X27: Researching | Y27: Whether pension/employee-benefits working group exists; best contact for content partnership
A28: Ring 1 | B28: CFA Society Luxembourg | C28: Luxembourg-wide | D28: Association / Federation / Professional body | E28: Federation | F28: High | G28: No contact | H28: 4 | I28: 3 | J28: 1 | K28: Mixed | L28: Weeks 8+ | M28: Test fit, visibility, and targeted user acquisition | N28: Exploratory call to identify best collaboration format | O28: We help internationally mobile finance professionals understand and organize pension rights scattered across the countries where they've built their careers | P28: Professional society for CFA charterholders and candidates since 2003; members are highly international finance professionals — exactly the profile with fragmented pension rights across multiple countries | Q28: Direct access to internationally mobile investment professionals; high pension-relevance; monthly educational conferences and networking events with 20-200 attendees | R28: Event / educational session / thought leadership / professional development content | S28: Membership open to CFA Institute members and candidates; events generally open to members; speaker proposals likely welcome | T28: Monthly conferences, networking events, newsletter, premium finance-professional audience, educational platform | U28: Pension-portability educational session for CFA members, practical guide for internationally mobile finance professionals, thought leadership content | W28: Check CFA Society events calendar; propose educational session on pension portability for CFA members | X28: Researching | Y28: Whether they host external speaker sessions; best contact for educational content proposals
A29: Ring 1 | B29: ILA – Institut Luxembourgeois des Administrateurs | C29: Luxembourg-wide | D29: Association / Federation / Professional body | E29: Federation | F29: High | G29: No contact | H29: 4 | I29: 3 | J29: 1 | K29: Mixed | L29: Weeks 8+ | M29: Test fit, visibility, and targeted user acquisition | N29: Exploratory call to identify best collaboration format | O29: Board directors with international careers have pension rights scattered across multiple countries. We help them track and organize those rights. | P29: Luxembourg's leading institute for corporate directors and governance professionals since 2005; 3,500+ members including board directors of international companies with careers spanning multiple countries | Q29: Access to 3,500+ senior governance professionals — exactly the profile with fragmented pension rights from multi-country board careers; training/certification events | R29: Training session / governance event / thought leadership / member benefit | S29: Membership-based; offers training, certification, and networking; open to speaker proposals | T29: 3,500+ member network, training events, governance certifications, newsletter, ecoDa European network | U29: Pension-portability session for board directors, practical guide for governance professionals, thought leadership | W29: Check ILA events calendar; propose governance-angle session on pension portability for board directors | X29: Researching | Y29: Whether they host external expert sessions in their training program; best contact for partnership
A30: Ring 1 | B30: APSI Luxembourg | C30: Luxembourg-wide | D30: Association / Federation / Professional body | E30: Federation | F30: Medium | G30: No contact | H30: 3 | I30: 2 | J30: 1 | K30: Mixed | L30: Weeks 8+ | M30: Test fit, visibility, and targeted user acquisition | N30: Exploratory call to identify best collaboration format | O30: We help employers support internationally mobile employees facing fragmented pension rights across countries | P30: Relevant if positioned as digital infrastructure / fintech / regtech / employee-digital-services topic | Q30: Reach Luxembourg tech community, digital leaders, and ecosystem visibility | R30: Ecosystem intro / event / visibility / tech-community content | S30: Likely association/community-based | T30: Tech visibility, digital ecosystem access, possible event channel | U30: Digital-use-case angle, startup/fintech story, product demo | W30: Check APSI events; explore digital-pension-tools angle for tech community | X30: Researching | Y30: Whether they are a strong enough GTM route versus only visibility
A31: Ring 1 | B31: INGSCI – Ingénieurs et Scientifiques du Luxembourg | C31: Luxembourg-wide | D31: Association / Federation / Professional body | E31: Federation | F31: Medium | G31: No contact | H31: 3 | I31: 2 | J31: 1 | K31: Mixed | L31: Weeks 8+ | M31: Test fit, visibility, and targeted user acquisition | N31: Exploratory call to identify best collaboration format | O31: Engineers who trained and worked in multiple countries before settling in Luxembourg have pension rights scattered across those systems. We help them organize and understand those rights. | P31: Luxembourg's voluntary association for engineers, architects, scientists and industrials; hosts the annual Journée de l'Ingénieur, conferences, and cross-border Saar-Lor-Lux events with engineering associations in Germany and France. Many members trained abroad. | Q31: Access to internationally trained engineers with careers spanning multiple countries; cross-border cooperation with DE/FR engineering associations directly touches pension fragmentation zone | R31: Conference session / Journée de l'Ingénieur / cross-border event / content | S31: Voluntary membership; hosts events at Forum da Vinci; open to speaker proposals | T31: Annual Journée de l'Ingénieur, conferences, cross-border Saar-Lor-Lux network, Forum da Vinci venue, publications | U31: Cross-border pension workshop for engineers, practical guide for mobile professionals, Saar-Lor-Lux themed session | W31: Contact INGSCI via secretariat; explore whether pension topic fits their Journée de l'Ingénieur or conference program | X31: Researching | Y31: Whether Journée de l'Ingénieur accepts external speakers; best contact at secretariat
A32: Ring 1 | B32: AMMD – Association des Médecins et Médecins-Dentistes | C32: Luxembourg-wide | D32: Association / Federation / Professional body | E32: Federation | F32: Medium | G32: No contact | H32: 3 | I32: 2 | J32: 1 | K32: Mixed | L32: Weeks 8+ | M32: Test fit, visibility, and targeted user acquisition | N32: Exploratory call to identify best collaboration format | O32: Doctors who trained and worked in other countries before practicing in Luxembourg have pension rights scattered across multiple systems. We help them track and organize those rights. | P32: Luxembourg's most representative medical association since 1904; key liaison between the medical profession, the Ministry of Health, and the CNS (national health fund). Doctors in LU are highly international — many trained abroad with pension rights in other countries. | Q32: Access to ~800-900 doctors and dentists, many of whom trained and worked abroad before settling in LU; direct link to CNS and social security system | R32: Member information service / event / content partnership | S32: Membership requires practicing authorization in LU; union-like structure; contact via secretariat | T32: Medical professional network, member communications, Scientific Council, link to CNS/Ministry of Health | U32: Pension-rights information resource for international doctors, practical guide for medical professionals relocating to/from LU | W32: Contact AMMD secretariat; explore whether pension/financial-planning content fits their member services | X32: Researching | Y32: Whether they provide member services beyond union representation; best contact for information partnership
A33: Ring 2 | B33: CCIPL / Portugal–Luxembourg Chamber (ccill.lu) | C33: PT | D33: Country / Bilateral Chamber | E33: Country Association | F33: High | G33: General contact | H33: 4 | I33: 5 | J33: 5 | K33: Expansion-bridge (Portugal; timed to Y1 window) | L33: Weeks 11–12 (Y1; Portugal expansion) | M33: Build corridor bridge for FR / PT / IT / UK / CH/ SP expansion | N33: Webinar / event / newsletter feature for the target community | O33: We help Portugal–Luxembourg professionals understand and organize pension rights across countries | P33: Highly relevant member/community topic for Portugal-linked entrepreneurs and professionals; fits their business support and matchmaking role | Q33: Reach Portugal-linked founders, professionals, firms, and their event/newsletter audience | R33: Event / content / community pilot / referrals | S33: Likely member-driven; collaboration may depend on format or sponsorship | T33: Community access, events, business introductions, newsletter potential, visibility | U33: Portugal–Luxembourg pension session, guide, pilot | V33: info@ccill.lu | W33: Prepare contact and draft offer now; outreach in Months 11–12 before Portugal expansion | X33: Researching | Y33: Whether speaking or content visibility needs membership or sponsor status or can start as external expert contribution
A34: Ring 2 | B34: Official Spanish Chamber of Commerce in Belgium and Luxembourg (e-camara.com) | C34: ES | D34: Country / Bilateral Chamber | E34: Country Association | F34: Medium-High | G34: General contact | H34: 3 | I34: 4 | J34: 5 | K34: Expansion-bridge (Spain; timed to Y1 window) | L34: weeks 19-20 (Y1; Spain expansion) | M34: Build corridor bridge for FR / PT / IT / UK / CH/ SP expansion | N34: Bilateral-community event and cross-country visibility | O34: We help internationally mobile professionals with Spain-linked careers organize pension rights across countries | P34: Relevant member/community topic for Spain-linked entrepreneurs and professionals; fits their business support and matchmaking role | Q34: Reach Spain-linked founders, professionals, firms, and their event/newsletter audience | R34: Event / content / community pilot / referrals | S34: Likely member-driven; collaboration may depend on format or sponsorship (direct contact?) | T34: Community access, events, business introductions, newsletter potential, visibility | U34: Spain–Lux session, guide, pilot group | V34: luxemburgo@e-camara.com | W34: Keep in tracker; do not prioritize in current wave unless Spain/UK track is confirmed | X34: Researching | Y34: Whether speaking or content visibility needs membership or sponsor status or can start as external expert contribution
A35: Ring 2 | B35: British Chamber of Commerce | C35: UK / EN-speaking | D35: International business community | E35: Country Community | F35: High | G35: Direct contact | H35: 4 | I35: 4 | J35: 5 | K35: Expansion-bridge (UK; timed to Y1 window) | L35: weeks 27-28 (Y1; UK expansion) | M35: Build corridor bridge for FR / PT / IT / UK / CH/ SP expansion | N35: Exploratory call to identify best collaboration format | O35: We help international professionals and employers navigate fragmented pension rights built across Europe | P35: We offer relevant member value for international companies and international employees; fits their event-based knowledge sharing | Q35: Reach English-speaking employers, expat professionals, HR contacts, and member companies through events and committees | R35: Event / content / community pilot / referrals | S35: Likely member-driven; collaboration may depend on format or sponsorship | T35: Community access, Events, business forums, member network | U35: Educational session, employer-benefit angle, guide, sharing news on changes in pension rights. | V35: Rebecca Kellagher — Manager — rebecca.kellagher@bcc.lu | W35: Contact BCC events team; propose pension-rights session for British expats in LU | X35: Researching | Y35: Whether speaking or content visibility needs membership or sponsor status or can start as external expert contribution
A36: Ring 2 | B36: Luxembourg-Italian Chamber of Commerce | C36: IT | D36: Country / Bilateral Chamber | E36: Country Association | F36: High | G36: Direct contact | H36: 4 | I36: 4 | J36: 5 | K36: Expansion-bridge (Italy; timed to Y1 window) | L36: Weeks 35–36 (Y1; Italy expansion) | M36: Build corridor bridge for FR / PT / IT / UK / CH/ SP expansion | N36: Bilateral-community event and cross-country visibility | O36: We help Italy–Luxembourg professionals understand and organize pension rights across countries | P36: Relevant topic for Italy-linked companies and professionals in Luxembourg, especially since Italy is one of our product expansion markets | Q36: Reach Italy-linked founders, professionals, firms, and their event/newsletter audience | R36: Event / content / community pilot / referrals | S36: Likely chamber-based; direct outreach possible | T36: Bilateral network, events, visibility, member access | U36: Italy–Lux pension education session, practical guide, pilot audience | V36: Luisa Castelli — Secrétaire général / Directeur — l.castelli@ccil.lu | W36: Prepare contact and draft offer now; outreach in Weeks 35–36 before Italy expansion | X36: Researching | Y36: Whether speaking or content visibility needs membership or sponsor status or can start as external expert contribution
